{"created":"2016-05-14T21:37:55.000Z","title":"GTA:VC All Missions in 2:58:29 (May 14th, 2016)","description":"Still doing Cone Crazy","gameName":"Grand Theft Auto: Vice City","game":"grand-theft-auto-vice-city","length":10792,"chat":[{"user":"Mhmd_FVC","color":"#556977","offset":691,"fragments":[{"text":"now back in MY prime that was doable without going as insane"}],"badges":[0]},{"user":"Mhmd_FVC","color":"#556977","offset":703,"fragments":[{"text":"back in fil's day do 12h"}],"badges":[0]},{"user":"CrazyCharlieH","color":"#0000FF","offset":721,"fragments":[{"text":"i remember 3h reset streams"}],"badges":[]},{"user":"CrazyCharlieH","color":"#0000FF","offset":725,"fragments":[{"text":"they take me back"}],"badges":[]},{"user":"Mhmd_FVC","color":"#556977","offset":734,"fragments":[{"text":"whenever CC is re-added to the start of the route omega"}],"badges":[0]},{"user":"jolzi","color":"#388585","offset":745,"fragments":[{"text":"billy jean "},{"text":"Kreygasm","emote":1}],"badges":[0]},{"user":"mr_ptp","color":"#1E90FF","offset":757,"fragments":[{"text":"is this mh's route with cone crazy at the beginning? "},{"text":"4Head","emote":2}],"badges":[]},{"user":"jolzi","color":"#388585","offset":773,"fragments":[{"text":"i need to do a new am run"}],"badges":[0]},{"user":"Mhmd_FVC","color":"#556977","offset":775,"fragments":[{"text":"I'll find a dank instapass"}],"badges":[0]},{"user":"jolzi","color":"#388585","offset":777,"fragments":[{"text":"to get sub beno"}],"badges":[0]},{"user":"jolzi","color":"#388585","offset":780,"fragments":[{"text":"at least"}],"badges":[0]},{"user":"Mhmd_FVC","color":"#556977","offset":784,"fragments":[{"text":"cone crazy with death row"}],"badges":[0]},{"user":"Mhmd_FVC","color":"#556977","offset":789,"fragments":[{"text":"or something"}],"badges":[0]},{"user":"jolzi","color":"#388585","offset":796,"fragments":[{"text":"why would you do cone crazy "},{"text":"DansGame","emote":3}],"badges":[0]},{"user":"jolzi","color":"#388585","offset":799,"fragments":[{"text":"early malibu?"}],"badges":[0]},{"user":"jolzi","color":"#388585","offset":812,"fragments":[{"text":"why not just run phil%"}],"badges":[0]},{"user":"Rapid_Influx","color":"#0000FF","offset":815,"fragments":[{"text":"Jolzi iirc you used to be a CC advocate"}],"badges":[]},{"user":"Rapid_Influx","color":"#0000FF","offset":827,"fragments":[{"text":"Fame changed you man "},{"text":"DansGame","emote":3}],"badges":[]},{"user":"jolzi","color":"#388585","offset":831,"fragments":[{"text":"i still love CC"}],"badges":[0]},{"user":"mr_ptp","color":"#1E90FF","offset":837,"fragments":[{"text":"phil% would be worse than any%"}],"badges":[]},{"user":"jolzi","color":"#388585","offset":842,"fragments":[{"text":"but i want people to do low% all missions"}],"badges":[0]},{"user":"mr_ptp","color":"#1E90FF","offset":842,"fragments":[{"text":"malibu missions sPuke"}],"badges":[]},{"user":"Mhmd_FVC","color":"#556977","offset":844,"fragments":[{"text":"one of my old routes had it so you'd do CC 8 times"}],"badges":[0]},{"user":"Mhmd_FVC","color":"#556977","offset":845,"fragments":[{"text":"not 9"}],"badges":[0]},{"user":"Mhmd_FVC","color":"#556977","offset":849,"fragments":[{"text":"before duping came along"}],"badges":[0]},{"user":"jolzi","color":"#388585","offset":853,"fragments":[{"text":"that means no CC and no USJ on hog tied"}],"badges":[0]},{"user":"Mhmd_FVC","color":"#556977","offset":854,"fragments":[{"text":"pretty good"}],"badges":[0]},{"user":"jolzi","color":"#388585","offset":876,"fragments":[{"text":"but mh 1x dirt ring is faster than 8x cc"}],"badges":[0]},{"user":"Mhmd_FVC","color":"#556977","offset":888,"fragments":[{"text":"true"}],"badges":[0]},{"user":"Mhmd_FVC","color":"#556977","offset":896,"fragments":[{"text":"I didn't consider it back then though"}],"badges":[0]},{"user":"jolzi","color":"#388585","offset":901,"fragments":[{"text":"whens AM route without hog tied USJ?"}],"badges":[0]},{"user":"Mhmd_FVC","color":"#556977","offset":909,"fragments":[{"text":"my PB doesn't have it"}],"badges":[0]},{"user":"jolzi","color":"#388585","offset":947,"fragments":[{"text":"good"}],"badges":[0]},{"user":"jolzi","color":"#388585","offset":957,"fragments":[{"text":"take a helicopter"}],"badges":[0]},{"user":"Mhmd_FVC","color":"#556977","offset":959,"fragments":[{"text":"you just leave the ramp on the left early"}],"badges":[0]},{"user":"Mhmd_FVC","color":"#556977","offset":962,"fragments":[{"text":"and you avoid slow-mo"}],"badges":[0]},{"user":"Mhmd_FVC","color":"#556977","offset":1026,"fragments":[{"text":"https://www.twitch.tv/mhmd_fvc/v/40630473"}],"badges":[0]},{"user":"Mhmd_FVC","color":"#556977","offset":1032,"fragments":[{"text":"idk if it was \"new\" but whatever"}],"badges":[0]},{"user":"mr_ptp","color":"#1E90FF","offset":1034,"fragments":[{"text":"https://twitter.com/KZ_Frew/status/731543125420847104"}],"badges":[]},{"user":"mr_ptp","color":"#1E90FF","offset":1036,"fragments":[{"text":"damn son"}],"badges":[]},{"user":"mr_ptp","color":"#1E90FF","offset":1048,"fragments":[{"text":"rip sub frew in am"}],"badges":[]},{"user":"joswie123","color":"#D2691E","offset":1058,"fragments":[{"text":"hello Omega!"}],"badges":[]},{"user":"cheeze____","color":"#DAA520","offset":1063,"fragments":[{"text":"Hellouw"}],"badges":[]},{"user":"Mhmd_FVC","color":"#556977","offset":1123,"fragments":[{"text":"ye that's what I do in 100%"}],"badges":[0]},{"user":"Ractrot","color":"#1E90FF","offset":1126,"fragments":[{"text":"you could, but frames"}],"badges":[]},{"user":"Mhmd_FVC","color":"#556977","offset":1134,"fragments":[{"text":"slide to get package + make replay without time after phone call"}],"badges":[0]},{"user":"Mhmd_FVC","color":"#556977","offset":1161,"fragments":[{"text":"fok this I'm gonna time that warp"}],"badges":[0]},{"user":"Mhmd_FVC","color":"#556977","offset":1163,"fragments":[{"text":"brb"}],"badges":[0]},{"user":"Ractrot","color":"#1E90FF","offset":1164,"fragments":[{"text":"just get great money drop rng"}],"badges":[]},{"user":"Ractrot","color":"#1E90FF","offset":1191,"fragments":[{"text":"should probably also time getting the vcn heli while you're at it"}],"badges":[]},{"user":"Mhmd_FVC","color":"#556977","offset":1205,"fragments":[{"text":"sure"}],"badges":[0]},{"user":"jolzi","color":"#388585","offset":1206,"fragments":[{"text":"sliding costs rta time"}],"badges":[0]},{"user":"jolzi","color":"#388585","offset":1215,"fragments":[{"text":"real time attack time "},{"text":"DansGame","emote":3}],"badges":[0]},{"user":"Elgu","color":"#1E90FF","offset":1217,"fragments":[{"text":"OMEGA"}],"badges":[0]},{"user":"jolzi","color":"#388585","offset":1217,"fragments":[{"text":"i mean real time"}],"badges":[0]},{"user":"joswie123","color":"#D2691E","offset":1239,"fragments":[{"text":"GLOD "},{"text":"Kreygasm","emote":1}],"badges":[]},{"user":"Elgu","color":"#1E90FF","offset":1253,"fragments":[{"text":"it was okay"}],"badges":[0]},{"user":"Elgu","color":"#1E90FF","offset":1258,"fragments":[{"text":"PBing is hard tho"}],"badges":[0]},{"user":"jolzi","color":"#388585","offset":1265,"fragments":[{"text":"elgu whens HL mac wr?"}],"badges":[0]},{"user":"Nick007J","color":"#008000","offset":1278,"fragments":[{"text":"hi gl"}],"badges":[]},{"user":"Elgu","color":"#1E90FF","offset":1278,"fragments":[{"text":"when someone buys a mac for me"}],"badges":[0]},{"user":"killerkieke","color":"#8A2BE2","offset":1278,"fragments":[{"text":"hello there!"}],"badges":[]},{"user":"Mhmd_FVC","color":"#556977","offset":1279,"fragments":[{"text":"HL PS2 or bust"}],"badges":[0]},{"user":"Elgu","color":"#1E90FF","offset":1285,"fragments":[{"text":"^"}],"badges":[0]},{"user":"jolzi","color":"#388585","offset":1293,"fragments":[{"text":"okok"}],"badges":[0]},{"user":"jolzi","color":"#388585","offset":1296,"fragments":[{"text":"whens HL linux wr"}],"badges":[0]},{"user":"cheeze____","color":"#DAA520","offset":1317,"fragments":[{"text":"miltWa","emote":4}],"badges":[]},{"user":"mr_ptp","color":"#1E90FF","offset":1370,"fragments":[{"text":"if you run games under wine aren't you supposed to submit them as emulator runs? sWonder"}],"badges":[]},{"user":"jolzi","color":"#388585","offset":1382,"fragments":[{"text":"wat"}],"badges":[0]},{"user":"jolzi","color":"#388585","offset":1386,"fragments":[{"text":"HL has a native port"}],"badges":[0]},{"user":"mr_ptp","color":"#1E90FF","offset":1388,"fragments":[{"text":"that's unrelated to half life"}],"badges":[]},{"user":"jolzi","color":"#388585","offset":1399,"fragments":[{"text":"technically wine is not an emulator"}],"badges":[0]},{"user":"jolzi","color":"#388585","offset":1405,"fragments":[{"text":"that's what the acronym WINE means"}],"badges":[0]},{"user":"mr_ptp","color":"#1E90FF","offset":1409,"fragments":[{"text":"i know"}],"badges":[]},{"user":"mr_ptp","color":"#1E90FF","offset":1420,"fragments":[{"text":"but it still is seen as emulator everywhere"}],"badges":[]},{"user":"jolzi","color":"#388585","offset":1428,"fragments":[{"text":"i would submit it as emu"}],"badges":[0]},{"user":"mr_ptp","color":"#1E90FF","offset":1440,"fragments":[{"text":"PC(emu) "},{"text":"4Head","emote":2}],"badges":[]},{"user":"jolzi","color":"#388585","offset":1443,"fragments":[{"text":"except for ~legit~ wine"}],"badges":[0]},{"user":"jolzi","color":"#388585","offset":1446,"fragments":[{"text":"like VC on mac"}],"badges":[0]},{"user":"jolzi","color":"#388585","offset":1461,"fragments":[{"text":"commercial wine package"}],"badges":[0]},{"user":"joswie123","color":"#D2691E","offset":1546,"fragments":[{"text":"@Pitp0 did you finish your sa already?"}],"badges":[]},{"user":"mr_ptp","color":"#1E90FF","offset":1578,"fragments":[{"text":"nah"}],"badges":[]},{"user":"mr_ptp","color":"#1E90FF","offset":1583,"fragments":[{"text":"i had to do some stuff irl"}],"badges":[]},{"user":"caine1232","color":"#0000FF","offset":1593,"fragments":[{"text":"GL omega, think you can do sub 3 this time?"}],"badges":[]},{"user":"jolzi","color":"#388585","offset":1607,"fragments":[{"text":"pitp0 i wouldn't quit before i get wr"}],"badges":[0]},{"user":"cheeze____","color":"#DAA520","offset":1629,"fragments":[{"text":"Street Cred "},{"text":"miltSmug","emote":5},{"text":" b"}],"badges":[]},{"user":"mr_ptp","color":"#1E90FF","offset":1632,"fragments":[{"text":"but my mom wanted to use pc "},{"text":">(","emote":6}],"badges":[]},{"user":"mr_ptp","color":"#1E90FF","offset":1643,"fragments":[{"text":"a program from virtual machine in fact"}],"badges":[]},{"user":"mr_ptp","color":"#1E90FF","offset":1665,"fragments":[{"text":"good luck keeping stream, game and virtual machine alive on 2 gigs of ram"}],"badges":[]},{"user":"mr_ptp","color":"#1E90FF","offset":1708,"fragments":[{"text":"fokn retarded companies don't update their sophisticated installers to 32bit"}],"badges":[]},{"user":"joswie123","color":"#D2691E","offset":1718,"fragments":[{"text":"\"what is your name? Tommy (Tommy drives off with his bike Kappa\""}],"badges":[]},{"user":"joswie123","color":"#D2691E","offset":1720,"fragments":[{"text":"Kappa","emote":7}],"badges":[]},{"user":"mr_ptp","color":"#1E90FF","offset":1850,"fragments":[{"text":"waste her WheelmanFace"}],"badges":[]},{"user":"Nozlar","color":"#8A2BE2","offset":1870,"fragments":[{"text":"do wanted levels hide rampages?"}],"badges":[8]},{"user":"Nozlar","color":"#8A2BE2","offset":1903,"fragments":[{"text":"dang"}],"badges":[8]},{"user":"jolzi","color":"#388585","offset":1913,"fragments":[{"text":"you could switch language to hide them"}],"badges":[0]},{"user":"jolzi","color":"#388585","offset":1917,"fragments":[{"text":"i did it in yesterdays run"}],"badges":[0]},{"user":"Ractrot","color":"#1E90FF","offset":1930,"fragments":[{"text":"using clothes replay and knocking her over in the cutscene would've probably helped"}],"badges":[]},{"user":"johnnykxd","color":"#008000","offset":1955,"fragments":[{"text":"hi gl"}],"badges":[]},{"user":"cheeze____","color":"#DAA520","offset":1971,"fragments":[{"text":"Damn "},{"text":"miltWa","emote":4}],"badges":[]},{"user":"johnnykxd","color":"#008000","offset":2030,"fragments":[{"text":"You have outdated WR"}],"badges":[]},{"user":"The_Surviv0r","color":"#FF4500","offset":2118,"fragments":[{"text":"so what part of the replay makes the the m60 shoot so fast?"}],"badges":[]},{"user":"Powdinet","color":"#0000FF","offset":2132,"fragments":[{"text":"WR is taken directly from speedrun.com, Mh just hasn't updated his time on the website"}],"badges":[]},{"user":"cheeze____","color":"#DAA520","offset":2163,"fragments":[{"text":"hahaahaha"}],"badges":[]},{"user":"The_Surviv0r","color":"#FF4500","offset":2188,"fragments":[{"text":"so gta logic is the cause?"}],"badges":[]},{"user":"JC75_","color":"#FF4500","offset":2199,"fragments":[{"text":"i think it does that because you basically don't have the animation of firing the M60 anymore"}],"badges":[]},{"user":"cheeze____","color":"#DAA520","offset":2208,"fragments":[{"text":"\"Ok, you're on your own from here!\" *lance jumps out of the helicopter and kills himself*"}],"badges":[]},{"user":"JC75_","color":"#FF4500","offset":2219,"fragments":[{"text":"so because you don't need to wait for the animation to reset, you can fire as fast as the framerate allows"}],"badges":[]},{"user":"JC75_","color":"#FF4500","offset":2223,"fragments":[{"text":"that's my theory anyway"}],"badges":[]},{"user":"tHmCS","color":"#00C5CC","offset":2227,"fragments":[{"text":"gl ømega "},{"text":"swordW","emote":9}],"badges":[]},{"user":"JC75_","color":"#FF4500","offset":2234,"fragments":[{"text":"swordW","emote":9}],"badges":[]},{"user":"cheeze____","color":"#DAA520","offset":2246,"fragments":[{"text":"Oh"}],"badges":[]},{"user":"The_Surviv0r","color":"#FF4500","offset":2255,"fragments":[{"text":"shit now we need to shoot without frame limiter"}],"badges":[]},{"user":"cheeze____","color":"#DAA520","offset":2263,"fragments":[{"text":"Just as funny "},{"text":"miltWa","emote":4},{"text":" "},{"text":"Kappa","emote":7}],"badges":[]},{"user":"tHmCS","color":"#00C5CC","offset":2273,"fragments":[{"text":"i did runs for 50 minutes earlier, then i had enough VC for the day"}],"badges":[]},{"user":"Nick007J","color":"#008000","offset":2273,"fragments":[{"text":"clothes pickup recreates player and it removes first person view, and game doesn't apply timer between shots thus allowing one shot per frame"}],"badges":[]},{"user":"tHmCS","color":"#00C5CC","offset":2283,"fragments":[{"text":"idk motivation is hard man"}],"badges":[]},{"user":"Nick007J","color":"#008000","offset":2284,"fragments":[{"text":"it looks especially great with grenades"}],"badges":[]},{"user":"Nick007J","color":"#008000","offset":2307,"fragments":[{"text":"yeah, without frame limiter it may look even more great I think"}],"badges":[]},{"user":"tHmCS","color":"#00C5CC","offset":2336,"fragments":[{"text":"a timeless classic"}],"badges":[]},{"user":"the_1826","color":null,"offset":2344,"fragments":[{"text":"Rial fresh! "},{"text":"FutureMan","emote":10}],"badges":[]},{"user":"JC75_","color":"#FF4500","offset":2357,"fragments":[{"text":"what about getting WR offline and not telling anyone the time "},{"text":"Kappa","emote":7}],"badges":[]},{"user":"Hellrider_23","color":"#B22222","offset":2360,"fragments":[{"text":"OneHand","emote":11}],"badges":[]},{"user":"tHmCS","color":"#00C5CC","offset":2367,"fragments":[{"text":"oh that was a good meme"}],"badges":[]},{"user":"the_1826","color":null,"offset":2372,"fragments":[{"text":"Guys,new twitch emotion: "},{"text":"FutureMan","emote":10},{"text":" - FutureMаn"}],"badges":[]},{"user":"Hellrider_23","color":"#B22222","offset":2381,"fragments":[{"text":"FutureMan","emote":10}],"badges":[]},{"user":"JC75_","color":"#FF4500","offset":2384,"fragments":[{"text":"new emotion"}],"badges":[]},{"user":"JC75_","color":"#FF4500","offset":2392,"fragments":[{"text":"that's a cool one though"}],"badges":[]},{"user":"JC75_","color":"#FF4500","offset":2393,"fragments":[{"text":"nice pixels"}],"badges":[]},{"user":"Hellrider_23","color":"#B22222","offset":2396,"fragments":[{"text":"FutureMan","emote":10},{"text":" "},{"text":"FutureMan","emote":10},{"text":" "},{"text":"FutureMan","emote":10}],"badges":[]},{"user":"Hellrider_23","color":"#B22222","offset":2401,"fragments":[{"text":"shitty emote "},{"text":"Kappa","emote":7}],"badges":[]},{"user":"the_1826","color":null,"offset":2401,"fragments":[{"text":"FutureMan","emote":10}],"badges":[]},{"user":"cheeze____","color":"#DAA520","offset":2419,"fragments":[{"text":"FutureMan","emote":10}],"badges":[]},{"user":"JC75_","color":"#FF4500","offset":2429,"fragments":[{"text":"ThePeter best emote"}],"badges":[]},{"user":"the_1826","color":null,"offset":2475,"fragments":[{"text":"Ghost controlling the boat "},{"text":"WutFace","emote":12}],"badges":[]},{"user":"the_1826","color":null,"offset":2505,"fragments":[{"text":"bi kul,bi kul! "},{"text":"PartyTime","emote":13}],"badges":[]},{"user":"jolzi","color":"#388585","offset":2509,"fragments":[{"text":"rip call"}],"badges":[0]},{"user":"jolzi","color":"#388585","offset":2517,"fragments":[{"text":"fake glod"}],"badges":[0]},{"user":"jolzi","color":"#388585","offset":2554,"fragments":[{"text":"i thought you have a new special route"}],"badges":[0]},{"user":"scha_de","color":"#FF4500","offset":2571,"fragments":[{"text":"were the kids in murica"}],"badges":[]},{"user":"jolzi","color":"#388585","offset":2577,"fragments":[{"text":"not going for aces strats "},{"text":"DansGame","emote":3}],"badges":[0]},{"user":"the_1826","color":null,"offset":2580,"fragments":[{"text":"Sir,no sir (That was joke,and you need to lauhgh)"}],"badges":[]},{"user":"mr_ptp","color":"#1E90FF","offset":2607,"fragments":[{"text":"xd"}],"badges":[]},{"user":"cheeze____","color":"#DAA520","offset":2608,"fragments":[{"text":"PogChamp","emote":14}],"badges":[]},{"user":"scha_de","color":"#FF4500","offset":2612,"fragments":[{"text":"rain is up"}],"badges":[]},{"user":"Mhmd_FVC","color":"#556977","offset":2649,"fragments":[{"text":"hmm"}],"badges":[0]},{"user":"Mhmd_FVC","color":"#556977","offset":2655,"fragments":[{"text":"I'll verify my own run I guess"}],"badges":[0]},{"user":"Mhmd_FVC","color":"#556977","offset":2659,"fragments":[{"text":"see the time update on the splits"}],"badges":[0]},{"user":"jolzi","color":"#388585","offset":2682,"fragments":[{"text":"oh dang"}],"badges":[0]},{"user":"jolzi","color":"#388585","offset":2685,"fragments":[{"text":"when did you pb?"}],"badges":[0]},{"user":"Powdinet","color":"#0000FF","offset":2694,"fragments":[{"text":"verifying your own run "},{"text":"DansGame","emote":3},{"text":" "},{"text":"DansGame","emote":3},{"text":" "},{"text":"DansGame","emote":3},{"text":" "},{"text":"DansGame","emote":3},{"text":" "},{"text":"DansGame","emote":3},{"text":" "},{"text":"DansGame","emote":3},{"text":" "},{"text":"DansGame","emote":3},{"text":" "},{"text":"DansGame","emote":3}],"badges":[]},{"user":"cheeze____","color":"#DAA520","offset":2694,"fragments":[{"text":"PogChamp","emote":14}],"badges":[]},{"user":"Mhmd_FVC","color":"#556977","offset":2696,"fragments":[{"text":"1h-2h ago"}],"badges":[0]},{"user":"the_1826","color":null,"offset":2702,"fragments":[{"text":"@mhmd_fvc hai,mihimet_fivisi "},{"text":"OneHand","emote":11}],"badges":[]},{"user":"Mhmd_FVC","color":"#556977","offset":2707,"fragments":[{"text":"ohai"}],"badges":[0]},{"user":"jolzi","color":"#388585","offset":2728,"fragments":[{"text":"nice"}],"badges":[0]},{"user":"jolzi","color":"#388585","offset":2747,"fragments":[{"text":"mh do you park the bike on sys in the same shitty way as omega did?"}],"badges":[0]},{"user":"Mhmd_FVC","color":"#556977","offset":2759,"fragments":[{"text":"idk I was timing stuff when he was doing SYS"}],"badges":[0]},{"user":"Mhmd_FVC","color":"#556977","offset":2770,"fragments":[{"text":"I'd wall grind it near ryton aide"}],"badges":[0]},{"user":"jolzi","color":"#388585","offset":2844,"fragments":[{"text":"aces strats: stop the bike infront of the tank to do the old park strats but don't get off"}],"badges":[0]},{"user":"jolzi","color":"#388585","offset":2855,"fragments":[{"text":"after you stopped for like 0.2 sec you drive a little forward"}],"badges":[0]},{"user":"asazin118","color":"#1E90FF","offset":2862,"fragments":[{"text":"Hello goodluck"}],"badges":[]},{"user":"jolzi","color":"#388585","offset":2865,"fragments":[{"text":"faster than shooting and bike stays alive"}],"badges":[0]},{"user":"jolzi","color":"#388585","offset":2896,"fragments":[{"text":"guy gets out of the tank because a vehicle was parked in front of it"}],"badges":[0]},{"user":"fruckiie","color":"#8A2BE2","offset":3005,"fragments":[{"text":"all these glods "},{"text":"triDANK","emote":15}],"badges":[]},{"user":"Mhmd_FVC","color":"#556977","offset":3012,"fragments":[{"text":"sounds good jolzi but I've never seen it"}],"badges":[0]},{"user":"St3nu","color":"#1E90FF","offset":3022,"fragments":[{"text":"Sup y'all"}],"badges":[]},{"user":"jolzi","color":"#388585","offset":3022,"fragments":[{"text":"aces was the only one doing it"}],"badges":[0]},{"user":"jolzi","color":"#388585","offset":3039,"fragments":[{"text":"and he only started doing it like 1 week before we started using the heli"}],"badges":[0]},{"user":"jolzi","color":"#388585","offset":3044,"fragments":[{"text":"so it didn't really spread"}],"badges":[0]},{"user":"Mhmd_FVC","color":"#556977","offset":3151,"fragments":[{"text":"Ractrot"}],"badges":[0]},{"user":"Ractrot","color":"#1E90FF","offset":3172,"fragments":[{"text":"Mhmd_FVC"}],"badges":[]},{"user":"Mhmd_FVC","color":"#556977","offset":3190,"fragments":[{"text":"getting heli after wife is 2m30 slower than going straight to diaz and all the stuff associated with the two"}],"badges":[0]},{"user":"cheeze____","color":"#DAA520","offset":3206,"fragments":[{"text":"Glod heaven "},{"text":"Kreygasm","emote":1}],"badges":[]},{"user":"Ractrot","color":"#1E90FF","offset":3215,"fragments":[{"text":"wow"}],"badges":[]},{"user":"mr_ptp","color":"#1E90FF","offset":3217,"fragments":[{"text":"wow"}],"badges":[]},{"user":"fruckiie","color":"#8A2BE2","offset":3217,"fragments":[{"text":"look at those hp hacks "},{"text":"bubKotaku","emote":16}],"badges":[]},{"user":"St3nu","color":"#1E90FF","offset":3218,"fragments":[{"text":"That was unexpected"}],"badges":[]},{"user":"Ractrot","color":"#1E90FF","offset":3282,"fragments":[{"text":"how's it that much?"}],"badges":[]},{"user":"Mhmd_FVC","color":"#556977","offset":3298,"fragments":[{"text":"hell if I know"}],"badges":[0]},{"user":"Mhmd_FVC","color":"#556977","offset":3305,"fragments":[{"text":"I compared what I just timed to my PB"}],"badges":[0]},{"user":"jolzi","color":"#388585","offset":3305,"fragments":[{"text":"Mhmd_FVC"}],"badges":[0]},{"user":"Mhmd_FVC","color":"#556977","offset":3309,"fragments":[{"text":"segment was fairly ok for both"}],"badges":[0]},{"user":"Mhmd_FVC","color":"#556977","offset":3311,"fragments":[{"text":"considering strats"}],"badges":[0]},{"user":"jolzi","color":"#388585","offset":3313,"fragments":[{"text":"have you timed the vehicles on this mission?"}],"badges":[0]},{"user":"Mhmd_FVC","color":"#556977","offset":3321,"fragments":[{"text":"no"}],"badges":[0]},{"user":"jolzi","color":"#388585","offset":3340,"fragments":[{"text":"burito vs anything + sentinel vs police heli vs police car"}],"badges":[0]},{"user":"mr_ptp","color":"#1E90FF","offset":3413,"fragments":[{"text":"at this rate you're going to bop frew "},{"text":"PogChamp","emote":14}],"badges":[]},{"user":"Mhmd_FVC","color":"#556977","offset":3415,"fragments":[{"text":"I take cop cars if I see one"}],"badges":[0]},{"user":"Mhmd_FVC","color":"#556977","offset":3417,"fragments":[{"text":"on the way"}],"badges":[0]},{"user":"Mhmd_FVC","color":"#556977","offset":3426,"fragments":[{"text":"nice omega"}],"badges":[0]},{"user":"jolzi","color":"#388585","offset":3436,"fragments":[{"text":"i feel like burito should be best"}],"badges":[0]},{"user":"CrazyCharlieH","color":"#0000FF","offset":3440,"fragments":[{"text":"oh shit, i thought mission failed for a sec there"}],"badges":[]},{"user":"Mhmd_FVC","color":"#556977","offset":3446,"fragments":[{"text":"there's that fixed spawn I guess ye"}],"badges":[0]},{"user":"jolzi","color":"#388585","offset":3453,"fragments":[{"text":"unless you have a vcn heli, then going for the police heli after candy"}],"badges":[0]},{"user":"Mhmd_FVC","color":"#556977","offset":3462,"fragments":[{"text":"I used to do that jolzi"}],"badges":[0]},{"user":"Mhmd_FVC","color":"#556977","offset":3464,"fragments":[{"text":"but it felt really slow"}],"badges":[0]},{"user":"jolzi","color":"#388585","offset":3472,"fragments":[{"text":"somebody needs to time that"}],"badges":[0]},{"user":"Imahoodkingho","color":null,"offset":3487,"fragments":[{"text":"run is looking great so far tho"}],"badges":[]},{"user":"jolzi","color":"#388585","offset":3489,"fragments":[{"text":"sentinel seems slow as shit"}],"badges":[0]},{"user":"scha_de","color":"#FF4500","offset":3508,"fragments":[{"text":"saying sentinel is slow "},{"text":"DansGame","emote":3}],"badges":[]},{"user":"jolzi","color":"#388585","offset":3510,"fragments":[{"text":"getting a cop car at the police station before pizza place might be better"}],"badges":[0]},{"user":"Imahoodkingho","color":null,"offset":3526,"fragments":[{"text":"nice job"}],"badges":[]},{"user":"mr_ptp","color":"#1E90FF","offset":3532,"fragments":[{"text":"isn't it locked sometimes?"}],"badges":[]},{"user":"jolzi","color":"#388585","offset":3539,"fragments":[{"text":"don't know"}],"badges":[0]},{"user":"Ractrot","color":"#1E90FF","offset":3543,"fragments":[{"text":"it is"}],"badges":[]},{"user":"Mhmd_FVC","color":"#556977","offset":3554,"fragments":[{"text":"as I discovered today "},{"text":"OpieOP","emote":17}],"badges":[0]},{"user":"cheeze____","color":"#DAA520","offset":3557,"fragments":[{"text":"BibleThump","emote":18},{"text":" "},{"text":"BibleThump","emote":18}],"badges":[]},{"user":"Imahoodkingho","color":null,"offset":3558,"fragments":[{"text":"i just watched mhmds run last night"}],"badges":[]},{"user":"fruckiie","color":"#8A2BE2","offset":3571,"fragments":[{"text":"whoa, finally not a glod R I P"}],"badges":[]},{"user":"Ractrot","color":"#1E90FF","offset":3596,"fragments":[{"text":"dang, not getting armor and health"}],"badges":[]},{"user":"jolzi","color":"#388585","offset":3600,"fragments":[{"text":"not getting the free armor "},{"text":"DansGame","emote":3}],"badges":[0]},{"user":"Mhmd_FVC","color":"#556977","offset":3601,"fragments":[{"text":"sWonder"}],"badges":[0]},{"user":"mr_ptp","color":"#1E90FF","offset":3607,"fragments":[{"text":"real mang mode"}],"badges":[]},{"user":"scha_de","color":"#FF4500","offset":3653,"fragments":[{"text":"not doing 360s in the heli sWonder"}],"badges":[]},{"user":"Mhmd_FVC","color":"#556977","offset":3653,"fragments":[{"text":"the swaggier armor"}],"badges":[0]},{"user":"mr_ptp","color":"#1E90FF","offset":3704,"fragments":[{"text":"call after awos and before mwtm?"}],"badges":[]},{"user":"jolzi","color":"#388585","offset":3705,"fragments":[{"text":"you could get armor with bike g-spotlight"}],"badges":[0]},{"user":"mr_ptp","color":"#1E90FF","offset":3708,"fragments":[{"text":"sounds like a cool 15s waste"}],"badges":[]},{"user":"jolzi","color":"#388585","offset":3711,"fragments":[{"text":"but who does that "},{"text":"EleGiggle","emote":19}],"badges":[0]},{"user":"mr_ptp","color":"#1E90FF","offset":3755,"fragments":[{"text":"oh, so not directly before mwtm"}],"badges":[]},{"user":"jolzi","color":"#388585","offset":3765,"fragments":[{"text":"Mhmd_FVC"}],"badges":[0]},{"user":"jolzi","color":"#388585","offset":3780,"fragments":[{"text":"whens getting clothes replay on the auto scroller flight"}],"badges":[0]},{"user":"jolzi","color":"#388585","offset":3788,"fragments":[{"text":"and do the 3 snapshots during the cutscene"}],"badges":[0]},{"user":"Imahoodkingho","color":null,"offset":3850,"fragments":[{"text":"HYPE"}],"badges":[]},{"user":"johnnykxd","color":"#008000","offset":3851,"fragments":[{"text":"Why you dont use helicopter?"}],"badges":[]},{"user":"mr_ptp","color":"#1E90FF","offset":3852,"fragments":[{"text":"my let's play was a garbage"}],"badges":[]},{"user":"mr_ptp","color":"#1E90FF","offset":3863,"fragments":[{"text":"sub potpo is more free than water"}],"badges":[]},{"user":"scha_de","color":"#FF4500","offset":3879,"fragments":[{"text":"water isnt free in many parts of the world"}],"badges":[]},{"user":"mr_ptp","color":"#1E90FF","offset":3885,"fragments":[{"text":"fok"}],"badges":[]},{"user":"Mhmd_FVC","color":"#556977","offset":3886,"fragments":[{"text":"idk jolzi"}],"badges":[0]},{"user":"Mhmd_FVC","color":"#556977","offset":3888,"fragments":[{"text":"is that a thing?"}],"badges":[0]},{"user":"johnnykxd","color":"#008000","offset":3890,"fragments":[{"text":"I see now. sorry"}],"badges":[]},{"user":"jolzi","color":"#388585","offset":3895,"fragments":[{"text":"not yet"}],"badges":[0]},{"user":"Ractrot","color":"#1E90FF","offset":3900,"fragments":[{"text":"zooming in during cutscene sounds tricky "},{"text":"OpieOP","emote":17}],"badges":[]},{"user":"Mhmd_FVC","color":"#556977","offset":3908,"fragments":[{"text":"probably"}],"badges":[0]},{"user":"jolzi","color":"#388585","offset":3920,"fragments":[{"text":"what clothes would you get?"}],"badges":[0]},{"user":"jolzi","color":"#388585","offset":3922,"fragments":[{"text":"golf?"}],"badges":[0]},{"user":"jolzi","color":"#388585","offset":3945,"fragments":[{"text":"or downtown clothes during recruitment drive"}],"badges":[0]},{"user":"Mhmd_FVC","color":"#556977","offset":3948,"fragments":[{"text":"uh"}],"badges":[0]},{"user":"Mhmd_FVC","color":"#556977","offset":3952,"fragments":[{"text":"yeah"}],"badges":[0]},{"user":"Mhmd_FVC","color":"#556977","offset":3955,"fragments":[{"text":"tracksuit"}],"badges":[0]},{"user":"Mhmd_FVC","color":"#556977","offset":3973,"fragments":[{"text":"also the warp after chase is ~7s faster with no package grabs"}],"badges":[0]},{"user":"Mhmd_FVC","color":"#556977","offset":3978,"fragments":[{"text":"so likely will not save time"}],"badges":[0]},{"user":"Mhmd_FVC","color":"#556977","offset":3981,"fragments":[{"text":"and you lose clothes replay"}],"badges":[0]},{"user":"Ractrot","color":"#1E90FF","offset":3997,"fragments":[{"text":"lol"}],"badges":[]},{"user":"scha_de","color":"#FF4500","offset":4001,"fragments":[{"text":"suxXx"}],"badges":[]},{"user":"Ractrot","color":"#1E90FF","offset":4006,"fragments":[{"text":"typical"}],"badges":[]},{"user":"DarkHayabuza1","color":null,"offset":4105,"fragments":[{"text":"cam "},{"text":"PogChamp","emote":14}],"badges":[]},{"user":"Mhmd_FVC","color":"#556977","offset":4116,"fragments":[{"text":"all thanks to cabmaggedon instapass"}],"badges":[0]},{"user":"Mhmd_FVC","color":"#556977","offset":4119,"fragments":[{"text":"(not tiren)"}],"badges":[0]},{"user":"jolzi","color":"#388585","offset":4128,"fragments":[{"text":"next time bail of the bike and run towards it. ~pre diaz zip strats~"}],"badges":[0]},{"user":"mr_ptp","color":"#1E90FF","offset":4128,"fragments":[{"text":"who even is tiren "},{"text":"OneHand","emote":11}],"badges":[]},{"user":"Imahoodkingho","color":null,"offset":4141,"fragments":[{"text":"lol @ mhmd"}],"badges":[]},{"user":"St3nu","color":"#1E90FF","offset":4162,"fragments":[{"text":"Nice. SmoothMove"}],"badges":[]},{"user":"cheeze____","color":"#DAA520","offset":4164,"fragments":[{"text":"LOL"}],"badges":[]},{"user":"mr_ptp","color":"#1E90FF","offset":4171,"fragments":[{"text":"taxi 3"}],"badges":[]},{"user":"mr_ptp","color":"#1E90FF","offset":4183,"fragments":[{"text":"used to leave you in the middle of nowhere"}],"badges":[]},{"user":"mr_ptp","color":"#1E90FF","offset":4198,"fragments":[{"text":"now it's instapassed with hit the courier which is very convenient"}],"badges":[]},{"user":"Mhmd_FVC","color":"#556977","offset":4264,"fragments":[{"text":"cba routing 100% for this stuff nowadays"}],"badges":[0]},{"user":"Mhmd_FVC","color":"#556977","offset":4268,"fragments":[{"text":"so I settled for missiones"}],"badges":[0]},{"user":"mr_ptp","color":"#1E90FF","offset":4297,"fragments":[{"text":"how bad is your pb? sWonder"}],"badges":[]},{"user":"mr_ptp","color":"#1E90FF","offset":4304,"fragments":[{"text":"omega"}],"badges":[]},{"user":"Imahoodkingho","color":null,"offset":4315,"fragments":[{"text":"this category and any% has came looooonng ways in the past year #conecrazy"}],"badges":[]},{"user":"jolzi","color":"#388585","offset":4321,"fragments":[{"text":"http://youtu.be/_cAbgFJcSwU"}],"badges":[0]},{"user":"Jazzy","color":"#CB01BA","offset":4326,"fragments":[{"text":"LilZ"}],"badges":[]},{"user":"Mhmd_FVC","color":"#556977","offset":4330,"fragments":[{"text":"100% more so"}],"badges":[0]},{"user":"Mhmd_FVC","color":"#556977","offset":4331,"fragments":[{"text":"I'd say"}],"badges":[0]},{"user":"Hellrider_23","color":"#B22222","offset":4333,"fragments":[{"text":"cmonBruh","emote":20}],"badges":[]},{"user":"Imahoodkingho","color":null,"offset":4341,"fragments":[{"text":"tru"}],"badges":[]},{"user":"Mhmd_FVC","color":"#556977","offset":4365,"fragments":[{"text":"I like how the dude ran you over jolzi"}],"badges":[0]},{"user":"jolzi","color":"#388585","offset":4371,"fragments":[{"text":"yeah"}],"badges":[0]},{"user":"jolzi","color":"#388585","offset":4383,"fragments":[{"text":"fucking faggio crew"}],"badges":[0]},{"user":"Imahoodkingho","color":null,"offset":4385,"fragments":[{"text":"lmao @ jolzi"}],"badges":[]},{"user":"mr_ptp","color":"#1E90FF","offset":4388,"fragments":[{"text":"i like how the dude took patriot after you had taken his faggio"}],"badges":[]},{"user":"jolzi","color":"#388585","offset":4399,"fragments":[{"text":"i didn't want to take the faggio"}],"badges":[0]},{"user":"Mhmd_FVC","color":"#556977","offset":4402,"fragments":[{"text":"\"u stil from me, i stil frum u\""}],"badges":[0]},{"user":"Imahoodkingho","color":null,"offset":4412,"fragments":[{"text":"karma bitch"}],"badges":[]},{"user":"Imahoodkingho","color":null,"offset":4414,"fragments":[{"text":"lol"}],"badges":[]},{"user":"Mhmd_FVC","color":"#556977","offset":4461,"fragments":[{"text":"hm"}],"badges":[0]},{"user":"Mhmd_FVC","color":"#556977","offset":4464,"fragments":[{"text":"how do you have so much ammo"}],"badges":[0]},{"user":"anti_","color":"#556977","offset":4468,"fragments":[{"text":"man"}],"badges":[21]},{"user":"anti_","color":"#556977","offset":4482,"fragments":[{"text":"i feel so dumb rn tbh"}],"badges":[21]},{"user":"cazpersky","color":"#FF0000","offset":4513,"fragments":[{"text":"Hey Omega, gl. No Four Iron duping today? "},{"text":"OpieOP","emote":17}],"badges":[]},{"user":"jolzi","color":"#388585","offset":4548,"fragments":[{"text":"back flat tire on hog tied is pgood btw"}],"badges":[0]},{"user":"anti_","color":"#556977","offset":4550,"fragments":[{"text":"i answered call that you hold into check out@ check in frames before mission passed"}],"badges":[21]},{"user":"mr_ptp","color":"#1E90FF","offset":4551,"fragments":[{"text":"AntiStreaks, karl was boasting about his pcj playground wr"}],"badges":[]},{"user":"anti_","color":"#556977","offset":4575,"fragments":[{"text":"karl is so great"}],"badges":[21]},{"user":"Mhmd_FVC","color":"#556977","offset":4598,"fragments":[{"text":"OpieOP","emote":17}],"badges":[0]},{"user":"Nimachakin","color":"#8A2BE2","offset":4602,"fragments":[{"text":"lol "},{"text":"4Head","emote":2}],"badges":[]},{"user":"Imahoodkingho","color":null,"offset":4609,"fragments":[{"text":"the vc pigs for ya"}],"badges":[]},{"user":"Hellrider_23","color":"#B22222","offset":4609,"fragments":[{"text":"MingLee","emote":22}],"badges":[]},{"user":"mr_ptp","color":"#1E90FF","offset":4618,"fragments":[{"text":"AntiStreaks do sumth, you like those free wrs"}],"badges":[]},{"user":"mr_ptp","color":"#1E90FF","offset":4626,"fragments":[{"text":"sumthn even"}],"badges":[]},{"user":"anti_","color":"#556977","offset":4634,"fragments":[{"text":"i dont feel like going again straight away"}],"badges":[21]},{"user":"anti_","color":"#556977","offset":4638,"fragments":[{"text":"maybe later/tomorrow"}],"badges":[21]},{"user":"anti_","color":"#556977","offset":4653,"fragments":[{"text":"i made way too many mistakes in that run too"}],"badges":[21]},{"user":"DoktorNick","color":"#00FF7F","offset":4780,"fragments":[{"text":"reh-pu-re-i"}],"badges":[]},{"user":"Nick007J","color":"#008000","offset":4820,"fragments":[{"text":"Kаppa Waste"}],"badges":[]},{"user":"Mhmd_FVC","color":"#556977","offset":4833,"fragments":[{"text":"grrrrrrrrrrrrrrrrüpies to abiüse"}],"badges":[0]},{"user":"mr_ptp","color":"#1E90FF","offset":4843,"fragments":[{"text":"don't spend all your money on weapons :^"}],"badges":[]},{"user":"Mhmd_FVC","color":"#556977","offset":4854,"fragments":[{"text":"how would you do that"}],"badges":[0]},{"user":"Mhmd_FVC","color":"#556977","offset":4864,"fragments":[{"text":"or better question"}],"badges":[0]},{"user":"Mhmd_FVC","color":"#556977","offset":4865,"fragments":[{"text":"why"}],"badges":[0]},{"user":"anti_","color":"#556977","offset":4865,"fragments":[{"text":"but mandüping autocide"}],"badges":[21]},{"user":"scha_de","color":"#FF4500","offset":4873,"fragments":[{"text":"noDuping"}],"badges":[]},{"user":"Mhmd_FVC","color":"#556977","offset":4912,"fragments":[{"text":"oh"}],"badges":[0]},{"user":"Mhmd_FVC","color":"#556977","offset":4915,"fragments":[{"text":"rip buying malibu"}],"badges":[0]},{"user":"mr_ptp","color":"#1E90FF","offset":4923,"fragments":[{"text":"when did you make this replay? sWonder"}],"badges":[]},{"user":"Mhmd_FVC","color":"#556977","offset":4929,"fragments":[{"text":"I had like 125k after ahod in my PB I think"}],"badges":[0]},{"user":"anti_","color":"#556977","offset":4937,"fragments":[{"text":"during fashtesht boat"}],"badges":[21]},{"user":"anti_","color":"#556977","offset":4941,"fragments":[{"text":"im guessing"}],"badges":[21]},{"user":"Mhmd_FVC","color":"#556977","offset":4944,"fragments":[{"text":"ye"}],"badges":[0]},{"user":"mr_ptp","color":"#1E90FF","offset":4946,"fragments":[{"text":"but he bought film studio with f3"}],"badges":[]},{"user":"mr_ptp","color":"#1E90FF","offset":4957,"fragments":[{"text":"at least it looked like it"}],"badges":[]},{"user":"anti_","color":"#556977","offset":4960,"fragments":[{"text":"you can replay buy stuff without saving a new replay"}],"badges":[21]},{"user":"mr_ptp","color":"#1E90FF","offset":4965,"fragments":[{"text":"no shit m8"}],"badges":[]},{"user":"anti_","color":"#556977","offset":4968,"fragments":[{"text":"f3 f3 f1 tab"}],"badges":[21]},{"user":"Sui_VT","color":"#DAA520","offset":4968,"fragments":[{"text":"kottiRiepu","emote":23}],"badges":[]},{"user":"Mhmd_FVC","color":"#556977","offset":4975,"fragments":[{"text":"so what are you saying"}],"badges":[0]},{"user":"anti_","color":"#556977","offset":5025,"fragments":[{"text":"hey mh"}],"badges":[21]},{"user":"Mhmd_FVC","color":"#556977","offset":5031,"fragments":[{"text":"hi"}],"badges":[0]},{"user":"Ractrot","color":"#1E90FF","offset":5031,"fragments":[{"text":"it can"}],"badges":[]},{"user":"anti_","color":"#556977","offset":5050,"fragments":[{"text":"if you by any chance start holding call button before you actually get a call, can you still hold that call?"}],"badges":[21]},{"user":"Mhmd_FVC","color":"#556977","offset":5063,"fragments":[{"text":"I've never tried it but probably not"}],"badges":[0]},{"user":"anti_","color":"#556977","offset":5070,"fragments":[{"text":"yeah"}],"badges":[21]},{"user":"anti_","color":"#556977","offset":5075,"fragments":[{"text":"i did that in vip and rip run"}],"badges":[21]},{"user":"Ractrot","color":"#1E90FF","offset":5086,"fragments":[{"text":"you can hold it"}],"badges":[]},{"user":"anti_","color":"#556977","offset":5094,"fragments":[{"text":"i didnt know that"}],"badges":[21]},{"user":"anti_","color":"#556977","offset":5099,"fragments":[{"text":"and i let go before mission passed"}],"badges":[21]},{"user":"Mhmd_FVC","color":"#556977","offset":5138,"fragments":[{"text":"should probably do CC :^)"}],"badges":[0]},{"user":"Mhmd_FVC","color":"#556977","offset":5187,"fragments":[{"text":"excellent idea"}],"badges":[0]},{"user":"mr_ptp","color":"#1E90FF","offset":5202,"fragments":[{"text":"ahod is 5k, autocide is 4k"}],"badges":[]},{"user":"Mhmd_FVC","color":"#556977","offset":5232,"fragments":[{"text":"or hold a call all through cc"}],"badges":[0]},{"user":"Mhmd_FVC","color":"#556977","offset":5353,"fragments":[{"text":"man oh man"}],"badges":[0]},{"user":"Imahoodkingho","color":null,"offset":5363,"fragments":[{"text":"right"}],"badges":[]},{"user":"Imahoodkingho","color":null,"offset":5368,"fragments":[{"text":"you got it homie"}],"badges":[]},{"user":"Mhmd_FVC","color":"#556977","offset":5397,"fragments":[{"text":"like 7?"}],"badges":[0]},{"user":"DoktorNick","color":"#00FF7F","offset":5399,"fragments":[{"text":"СОПЕ СРАЗУ"}],"badges":[]},{"user":"Mhmd_FVC","color":"#556977","offset":5399,"fragments":[{"text":"I guess"}],"badges":[0]},{"user":"Mhmd_FVC","color":"#556977","offset":5422,"fragments":[{"text":"or 6"}],"badges":[0]},{"user":"Imahoodkingho","color":null,"offset":5432,"fragments":[{"text":"i was thinking 6"}],"badges":[]},{"user":"Mhmd_FVC","color":"#556977","offset":5440,"fragments":[{"text":"ye"}],"badges":[0]},{"user":"下痢","color":"#008000","offset":5490,"fragments":[{"text":"stopS"}],"badges":[]},{"user":"Mhmd_FVC","color":"#556977","offset":5518,"fragments":[{"text":"21s"}],"badges":[0]},{"user":"Mhmd_FVC","color":"#556977","offset":5519,"fragments":[{"text":"do 18s"}],"badges":[0]},{"user":"wewobulost","color":"#FF0000","offset":5524,"fragments":[{"text":"cone craizee"}],"badges":[]},{"user":"wewobulost","color":"#FF0000","offset":5542,"fragments":[{"text":"my ps3 is fucked "},{"text":":(","emote":24}],"badges":[]},{"user":"Imahoodkingho","color":null,"offset":5553,"fragments":[{"text":"them cones drive me craziiiiii"}],"badges":[]},{"user":"DoktorNick","color":"#00FF7F","offset":5561,"fragments":[{"text":"You can have mine"}],"badges":[]},{"user":"wewobulost","color":"#FF0000","offset":5587,"fragments":[{"text":"i dont even want it, just wanted to sell it but now its useless :*"}],"badges":[]},{"user":"DoktorNick","color":"#00FF7F","offset":5597,"fragments":[{"text":"I wonder if he ever fell off the roof and while doing CC"}],"badges":[]},{"user":"Imahoodkingho","color":null,"offset":5607,"fragments":[{"text":"im sure many has"}],"badges":[]},{"user":"wewobulost","color":"#FF0000","offset":5620,"fragments":[{"text":"slammed it, wasnt even me"}],"badges":[]},{"user":"Mhmd_FVC","color":"#556977","offset":5644,"fragments":[{"text":"nais"}],"badges":[0]},{"user":"anti_","color":"#556977","offset":5645,"fragments":[{"text":"gg"}],"badges":[21]},{"user":"wewobulost","color":"#FF0000","offset":5645,"fragments":[{"text":"gg"}],"badges":[]},{"user":"jolzi","color":"#388585","offset":5650,"fragments":[{"text":"damn people from a european country starting with F"}],"badges":[0]},{"user":"Pstol12","color":null,"offset":5652,"fragments":[{"text":"lol"}],"badges":[]},{"user":"mr_ptp","color":"#1E90FF","offset":5654,"fragments":[{"text":"PogChamp","emote":14},{"text":" //"}],"badges":[]},{"user":"wewobulost","color":"#FF0000","offset":5678,"fragments":[{"text":"Kappa","emote":7},{"text":" "},{"text":"Kappa","emote":7}],"badges":[]},{"user":"WhyAmIMrPink","color":"#FF69B4","offset":5682,"fragments":[{"text":"jolzi, I don't think Omega appreciates it that you hate people from Finland "},{"text":"Kappa","emote":7}],"badges":[]},{"user":"wewobulost","color":"#FF0000","offset":5693,"fragments":[{"text":"would work, then put as no return"}],"badges":[]},{"user":"wewobulost","color":"#FF0000","offset":5707,"fragments":[{"text":"the ps3 looks ok"}],"badges":[]},{"user":"wewobulost","color":"#FF0000","offset":5713,"fragments":[{"text":"not like its busted"}],"badges":[]},{"user":"wewobulost","color":"#FF0000","offset":5726,"fragments":[{"text":"ehh i want to make some money"}],"badges":[]},{"user":"anti_","color":"#556977","offset":5726,"fragments":[{"text":"not ones on 3.55 cfw"}],"badges":[21]},{"user":"TheChickenMuncher","color":"#8A2BE2","offset":5749,"fragments":[{"text":"So are you gonna be getting all the phone calls one after the other?"}],"badges":[]},{"user":"wewobulost","color":"#FF0000","offset":5760,"fragments":[{"text":"pretty much"}],"badges":[]},{"user":"mimous02","color":"#0000FF","offset":5761,"fragments":[{"text":"hi everyone "},{"text":"OpieOP","emote":17},{"text":" /"}],"badges":[]},{"user":"Graved","color":"#0000FF","offset":5804,"fragments":[{"text":"\"Oh my gawd, dey gat a helicopur\" "},{"text":"OpieOP","emote":17}],"badges":[]},{"user":"scha_de","color":"#FF4500","offset":5830,"fragments":[{"text":"the assassin caller sounds a bit like cortez"}],"badges":[]},{"user":"mimous02","color":"#0000FF","offset":5834,"fragments":[{"text":"it's good"}],"badges":[]},{"user":"Mhmd_FVC","color":"#556977","offset":5847,"fragments":[{"text":"buying with the boat sWonder"}],"badges":[0]},{"user":"anti_","color":"#556977","offset":5851,"fragments":[{"text":"brought the boat with"}],"badges":[21]},{"user":"wewobulost","color":"#FF0000","offset":5852,"fragments":[{"text":"lmao"}],"badges":[]},{"user":"anti_","color":"#556977","offset":5854,"fragments":[{"text":"SeemsGood","emote":25}],"badges":[21]},{"user":"wewobulost","color":"#FF0000","offset":5856,"fragments":[{"text":"nice boat"}],"badges":[]},{"user":"mimous02","color":"#0000FF","offset":5863,"fragments":[{"text":"boat strats"}],"badges":[]},{"user":"patrick_gta","color":"#D2691E","offset":5897,"fragments":[{"text":"taking the call during the buying cs gives you control after the call ended, right?"}],"badges":[]},{"user":"mimous02","color":"#0000FF","offset":5897,"fragments":[{"text":"the manilla blilla"}],"badges":[]},{"user":"mr_ptp","color":"#1E90FF","offset":5910,"fragments":[{"text":"sPuke"}],"badges":[]},{"user":"mr_ptp","color":"#1E90FF","offset":5912,"fragments":[{"text":"sPuke sPuke"}],"badges":[]},{"user":"mr_ptp","color":"#1E90FF","offset":5915,"fragments":[{"text":"sPuke sPuke sPuke"}],"badges":[]},{"user":"mr_ptp","color":"#1E90FF","offset":5917,"fragments":[{"text":"sPuke sPuke"}],"badges":[]},{"user":"mr_ptp","color":"#1E90FF","offset":5919,"fragments":[{"text":"sPuke"}],"badges":[]},{"user":"Marlboro_Ford","color":"#FF4500","offset":5928,"fragments":[{"text":"I let you have that one"}],"badges":[]},{"user":"mimous02","color":"#0000FF","offset":5938,"fragments":[{"text":"everyone respects potpo enough to not break his pyramide "},{"text":"Keepo","emote":26}],"badges":[]},{"user":"Mhmd_FVC","color":"#556977","offset":5945,"fragments":[{"text":"there's a way to make him not do that"}],"badges":[0]},{"user":"anti_","color":"#556977","offset":5952,"fragments":[{"text":"mh"}],"badges":[21]},{"user":"anti_","color":"#556977","offset":5954,"fragments":[{"text":"tell"}],"badges":[21]},{"user":"mr_ptp","color":"#1E90FF","offset":5960,"fragments":[{"text":"or everyone hates cam enough to not break pyramide for him"}],"badges":[]},{"user":"LethalGuestbook85","color":"#2E8B57","offset":5968,"fragments":[{"text":"camJones"}],"badges":[]},{"user":"patrick_gta","color":"#D2691E","offset":5976,"fragments":[{"text":"so the plan would be holding the payphone call until om=0, then buying Malibu and taking the call during the buying cutscene"}],"badges":[]},{"user":"mr_ptp","color":"#1E90FF","offset":5980,"fragments":[{"text":"WOW"}],"badges":[]},{"user":"TheChickenMuncher","color":"#8A2BE2","offset":5986,"fragments":[{"text":"Holy"}],"badges":[]},{"user":"Impossible2495","color":"#FF69B4","offset":5987,"fragments":[{"text":"LOL"}],"badges":[]},{"user":"anti_","color":"#556977","offset":5989,"fragments":[{"text":"5 star fuuuhhhhn"}],"badges":[21]},{"user":"wewobulost","color":"#FF0000","offset":5989,"fragments":[{"text":"fbi almost fucked you up"}],"badges":[]},{"user":"mimous02","color":"#0000FF","offset":6000,"fragments":[{"text":"fbi set me up"}],"badges":[]},{"user":"TheChickenMuncher","color":"#8A2BE2","offset":6011,"fragments":[{"text":"Nice try fbi"}],"badges":[]},{"user":"Ractrot","color":"#1E90FF","offset":6019,"fragments":[{"text":"the mission ending breaks the call i think"}],"badges":[]},{"user":"anti_","color":"#556977","offset":6038,"fragments":[{"text":"yeah"}],"badges":[21]},{"user":"Mhmd_FVC","color":"#556977","offset":6040,"fragments":[{"text":"basically just make sure he is able to see you, so don't take corners as quickly and stuff"}],"badges":[0]},{"user":"mr_ptp","color":"#1E90FF","offset":6041,"fragments":[{"text":"welcome to all missions speerdunning"}],"badges":[]},{"user":"Mhmd_FVC","color":"#556977","offset":6052,"fragments":[{"text":"and wait a little before running to the exit"}],"badges":[0]},{"user":"mr_ptp","color":"#1E90FF","offset":6055,"fragments":[{"text":"or rush to the exit"}],"badges":[]},{"user":"Mhmd_FVC","color":"#556977","offset":6067,"fragments":[{"text":"inconsistint"}],"badges":[0]},{"user":"mr_ptp","color":"#1E90FF","offset":6072,"fragments":[{"text":"he will spawn behind you like bank manager on the job for example"}],"badges":[]},{"user":"wewobulost","color":"#FF0000","offset":6077,"fragments":[{"text":"low on ammo? dont be ridiculous "},{"text":"OpieOP","emote":17}],"badges":[]},{"user":"mr_ptp","color":"#1E90FF","offset":6091,"fragments":[{"text":"if you're fast it's consistent"}],"badges":[]},{"user":"patrick_gta","color":"#D2691E","offset":6095,"fragments":[{"text":"I'll try my strat idea and record"}],"badges":[]},{"user":"Mhmd_FVC","color":"#556977","offset":6100,"fragments":[{"text":"you're calling me slow?"}],"badges":[0]},{"user":"Mhmd_FVC","color":"#556977","offset":6103,"fragments":[{"text":"SmoothMove"}],"badges":[0]},{"user":"mr_ptp","color":"#1E90FF","offset":6105,"fragments":[{"text":"OneHand","emote":11}],"badges":[]},{"user":"Marlboro_Ford","color":"#FF4500","offset":6117,"fragments":[{"text":"mostly slow"}],"badges":[]},{"user":"mr_ptp","color":"#1E90FF","offset":6119,"fragments":[{"text":"it works better for me than babysitting him"}],"badges":[]},{"user":"mr_ptp","color":"#1E90FF","offset":6125,"fragments":[{"text":"and dying to 500 cops standing in the corridor"}],"badges":[]},{"user":"anti_","color":"#556977","offset":6128,"fragments":[{"text":"oh yeah during my run today on two bit hit i forgot to get the cuban outfit"}],"badges":[21]},{"user":"jolzi","color":"#388585","offset":6129,"fragments":[{"text":"killing people instead just running out "},{"text":"DansGame","emote":3}],"badges":[0]},{"user":"anti_","color":"#556977","offset":6139,"fragments":[{"text":"and was confused when i got to the funeral nobody was there"}],"badges":[21]},{"user":"wewobulost","color":"#FF0000","offset":6141,"fragments":[{"text":"nice cheats"}],"badges":[]},{"user":"scha_de","color":"#FF4500","offset":6144,"fragments":[{"text":"what is your driving?"}],"badges":[]},{"user":"mr_ptp","color":"#1E90FF","offset":6146,"fragments":[{"text":"nice save"}],"badges":[]},{"user":"Impossible2495","color":"#FF69B4","offset":6146,"fragments":[{"text":"omg"}],"badges":[]},{"user":"Mhmd_FVC","color":"#556977","offset":6148,"fragments":[{"text":"fok"}],"badges":[0]},{"user":"mimous02","color":"#0000FF","offset":6159,"fragments":[{"text":"CLENCHED"}],"badges":[]},{"user":"anti_","color":"#556977","offset":6163,"fragments":[{"text":"this is worse than copland"}],"badges":[21]},{"user":"anti_","color":"#556977","offset":6168,"fragments":[{"text":"because no glitched shit\\"}],"badges":[21]},{"user":"mr_ptp","color":"#1E90FF","offset":6170,"fragments":[{"text":"this is the worst mission in the game tbh"}],"badges":[]},{"user":"Mhmd_FVC","color":"#556977","offset":6187,"fragments":[{"text":"no"}],"badges":[0]},{"user":"wewobulost","color":"#FF0000","offset":6198,"fragments":[{"text":"demo man"}],"badges":[]},{"user":"anti_","color":"#556977","offset":6201,"fragments":[{"text":"^"}],"badges":[21]},{"user":"mr_ptp","color":"#1E90FF","offset":6205,"fragments":[{"text":"4Head","emote":2}],"badges":[]},{"user":"anti_","color":"#556977","offset":6206,"fragments":[{"text":"was gonna say that"}],"badges":[21]},{"user":"mimous02","color":"#0000FF","offset":6214,"fragments":[{"text":"demo man is meh"}],"badges":[]},{"user":"wewobulost","color":"#FF0000","offset":6216,"fragments":[{"text":"not hard, but boring as shit"}],"badges":[]},{"user":"Impossible2495","color":"#FF69B4","offset":6218,"fragments":[{"text":"my worst mission is where u need to save lance"}],"badges":[]},{"user":"scha_de","color":"#FF4500","offset":6226,"fragments":[{"text":"demo man was so difficult when i played this on ps2"}],"badges":[]},{"user":"wewobulost","color":"#FF0000","offset":6231,"fragments":[{"text":"i remember demo man my first time"}],"badges":[]},{"user":"mr_ptp","color":"#1E90FF","offset":6234,"fragments":[{"text":"death row is ez with heli"}],"badges":[]},{"user":"wewobulost","color":"#FF0000","offset":6237,"fragments":[{"text":"just the controls"}],"badges":[]},{"user":"scha_de","color":"#FF4500","offset":6237,"fragments":[{"text":"were you waiting for eom call there, omega? "},{"text":"MingLee","emote":22}],"badges":[]},{"user":"mr_ptp","color":"#1E90FF","offset":6239,"fragments":[{"text":"cop land is ez with heli"}],"badges":[]},{"user":"wewobulost","color":"#FF0000","offset":6248,"fragments":[{"text":"and the damn guards kept shooting me up"}],"badges":[]},{"user":"anti_","color":"#556977","offset":6257,"fragments":[{"text":"potpo"}],"badges":[21]},{"user":"anti_","color":"#556977","offset":6260,"fragments":[{"text":"pley any%"}],"badges":[21]},{"user":"Mhmd_FVC","color":"#556977","offset":6261,"fragments":[{"text":"I can attest to the fact that the worst mission is The Job"}],"badges":[0]},{"user":"Mhmd_FVC","color":"#556977","offset":6276,"fragments":[{"text":"no other mission loves to crash and softlock as much as that one"}],"badges":[0]},{"user":"wewobulost","color":"#FF0000","offset":6288,"fragments":[{"text":"it was me and my cousin trying it, i had the arrows, since i didnt know wasd, and me cousin has the numpad"}],"badges":[]},{"user":"mr_ptp","color":"#1E90FF","offset":6290,"fragments":[{"text":"never had job crash on me "},{"text":"OpieOP","emote":17}],"badges":[]},{"user":"Mhmd_FVC","color":"#556977","offset":6295,"fragments":[{"text":"lucky"}],"badges":[0]},{"user":"Mhmd_FVC","color":"#556977","offset":6302,"fragments":[{"text":"also"}],"badges":[0]},{"user":"anti_","color":"#556977","offset":6308,"fragments":[{"text":"ive had it softlock as a kid"}],"badges":[21]},{"user":"Mhmd_FVC","color":"#556977","offset":6308,"fragments":[{"text":"random deaths of cam and bank manager"}],"badges":[0]},{"user":"anti_","color":"#556977","offset":6310,"fragments":[{"text":"on ps2"}],"badges":[21]},{"user":"Mhmd_FVC","color":"#556977","offset":6313,"fragments":[{"text":"when going into the elevator"}],"badges":[0]},{"user":"mr_ptp","color":"#1E90FF","offset":6329,"fragments":[{"text":"i'd still rather do the job over and over again than no escape"}],"badges":[]},{"user":"wewobulost","color":"#FF0000","offset":6333,"fragments":[{"text":"gta vee "},{"text":"<3","emote":27}],"badges":[]},{"user":"mr_ptp","color":"#1E90FF","offset":6343,"fragments":[{"text":"the job at least has some dank dialogues"}],"badges":[]},{"user":"Mhmd_FVC","color":"#556977","offset":6347,"fragments":[{"text":"that's only bcuz u succ"}],"badges":[0]},{"user":"anti_","color":"#556977","offset":6365,"fragments":[{"text":"no escape has some dank dialogue"}],"badges":[21]},{"user":"anti_","color":"#556977","offset":6369,"fragments":[{"text":"\"im busting you out\""}],"badges":[21]},{"user":"wewobulost","color":"#FF0000","offset":6372,"fragments":[{"text":"wtf"}],"badges":[]},{"user":"killerkieke","color":"#8A2BE2","offset":6375,"fragments":[{"text":"wut"}],"badges":[]},{"user":"Mhmd_FVC","color":"#556977","offset":6376,"fragments":[{"text":"sWonder sWonder sWonder sWonder sWonder sWonder sWonder sWonder sWonder sWonder sWonder"}],"badges":[0]},{"user":"mr_ptp","color":"#1E90FF","offset":6388,"fragments":[{"text":"nice 0 stars sWonder"}],"badges":[]},{"user":"wewobulost","color":"#FF0000","offset":6397,"fragments":[{"text":"you didnt teleport from inside"}],"badges":[]},{"user":"wewobulost","color":"#FF0000","offset":6411,"fragments":[{"text":"so maybe you killed that cop"}],"badges":[]},{"user":"m00nchile85","color":"#0000FF","offset":6440,"fragments":[{"text":"yo omega, hi chat"}],"badges":[0]},{"user":"Mhmd_FVC","color":"#556977","offset":6445,"fragments":[{"text":"ey m00n"}],"badges":[0]},{"user":"anti_","color":"#556977","offset":6448,"fragments":[{"text":"hey m00n"}],"badges":[21]},{"user":"wewobulost","color":"#FF0000","offset":6449,"fragments":[{"text":"hi"}],"badges":[]},{"user":"Marlboro_Ford","color":"#FF4500","offset":6455,"fragments":[{"text":"m00n"}],"badges":[]},{"user":"Imahoodkingho","color":null,"offset":6459,"fragments":[{"text":"what up m00n"}],"badges":[]},{"user":"m00nchile85","color":"#0000FF","offset":6463,"fragments":[{"text":"new AM rekky MH?"}],"badges":[0]},{"user":"Heinki","color":"#FF0000","offset":6481,"fragments":[{"text":"Heads up Omega,"}],"badges":[0]},{"user":"Heinki","color":"#FF0000","offset":6491,"fragments":[{"text":"YOur brother paul is on the way over I repeat, find paul"}],"badges":[0]},{"user":"Heinki","color":"#FF0000","offset":6497,"fragments":[{"text":"I will monitor your situation from HQ"}],"badges":[0]},{"user":"Heinki","color":"#FF0000","offset":6500,"fragments":[{"text":"FrankerZ","emote":28}],"badges":[0]},{"user":"Heinki","color":"#FF0000","offset":6533,"fragments":[{"text":"Moscow was nice "},{"text":"Kreygasm","emote":1}],"badges":[0]},{"user":"Heinki","color":"#FF0000","offset":6544,"fragments":[{"text":"just saw asmall amount but next time "},{"text":"FrankerZ","emote":28}],"badges":[0]},{"user":"Heinki","color":"#FF0000","offset":6553,"fragments":[{"text":"TOmorrow the competition starts and everything so it will be interesting"}],"badges":[0]},{"user":"Heinki","color":"#FF0000","offset":6562,"fragments":[{"text":"or more like warmup and planning + opening ceremony."}],"badges":[0]},{"user":"Imahoodkingho","color":null,"offset":6598,"fragments":[{"text":"is KZ_FREW still running now a days?"}],"badges":[]},{"user":"anti_","color":"#556977","offset":6608,"fragments":[{"text":"he just came back"}],"badges":[21]},{"user":"mr_ptp","color":"#1E90FF","offset":6608,"fragments":[{"text":"he just came back to vc running"}],"badges":[]},{"user":"Imahoodkingho","color":null,"offset":6612,"fragments":[{"text":"nice"}],"badges":[]},{"user":"mr_ptp","color":"#1E90FF","offset":6613,"fragments":[{"text":"sWonder"}],"badges":[]},{"user":"anti_","color":"#556977","offset":6638,"fragments":[{"text":"i guess you could say"}],"badges":[21]},{"user":"anti_","color":"#556977","offset":6642,"fragments":[{"text":"a frew days ago"}],"badges":[21]},{"user":"Imahoodkingho","color":null,"offset":6648,"fragments":[{"text":"lmao @ anti"}],"badges":[]},{"user":"mr_ptp","color":"#1E90FF","offset":6649,"fragments":[{"text":"SoBayed","emote":29}],"badges":[]},{"user":"Marlboro_Ford","color":"#FF4500","offset":6666,"fragments":[{"text":"sPuke"}],"badges":[]},{"user":"mr_ptp","color":"#1E90FF","offset":6728,"fragments":[{"text":"has anyone timed TBH heli vs infernus?"}],"badges":[]},{"user":"anti_","color":"#556977","offset":6746,"fragments":[{"text":"no"}],"badges":[21]},{"user":"Mhmd_FVC","color":"#556977","offset":6750,"fragments":[{"text":"you can"}],"badges":[0]},{"user":"Mhmd_FVC","color":"#556977","offset":6755,"fragments":[{"text":"if your route uses a heli"}],"badges":[0]},{"user":"anti_","color":"#556977","offset":6762,"fragments":[{"text":"but i imagine using it between then and cop land would be bahd"}],"badges":[21]},{"user":"mr_ptp","color":"#1E90FF","offset":6768,"fragments":[{"text":"i only timed that with some packages i pick up in hundo"}],"badges":[]},{"user":"Imahoodkingho","color":null,"offset":6768,"fragments":[{"text":"who won the trilogy race? i watched omega up untill san andreas"}],"badges":[]},{"user":"mr_ptp","color":"#1E90FF","offset":6775,"fragments":[{"text":"with those packages heli was slower"}],"badges":[]},{"user":"mr_ptp","color":"#1E90FF","offset":6783,"fragments":[{"text":"but that's quite obvious "},{"text":"OpieOP","emote":17}],"badges":[]},{"user":"mr_ptp","color":"#1E90FF","offset":6799,"fragments":[{"text":"im doing tbh right after copland"}],"badges":[]},{"user":"jolzi","color":"#388585","offset":6802,"fragments":[{"text":"at least you didn't run yourself over"}],"badges":[0]},{"user":"anti_","color":"#556977","offset":6807,"fragments":[{"text":"better than mh"}],"badges":[21]},{"user":"Mhmd_FVC","color":"#556977","offset":6807,"fragments":[{"text":"how the hell did that work"}],"badges":[0]},{"user":"Imahoodkingho","color":null,"offset":6812,"fragments":[{"text":"lmao"}],"badges":[]},{"user":"Heinki","color":"#FF0000","offset":6815,"fragments":[{"text":"MH"}],"badges":[0]},{"user":"Mhmd_FVC","color":"#556977","offset":6816,"fragments":[{"text":"way far left"}],"badges":[0]},{"user":"Heinki","color":"#FF0000","offset":6817,"fragments":[{"text":"Hi "},{"text":"OneHand","emote":11}],"badges":[0]},{"user":"Mhmd_FVC","color":"#556977","offset":6820,"fragments":[{"text":"heinki"}],"badges":[0]},{"user":"Mhmd_FVC","color":"#556977","offset":6822,"fragments":[{"text":"eeeeeey"}],"badges":[0]},{"user":"Heinki","color":"#FF0000","offset":6839,"fragments":[{"text":"yesDuping yesDuping yesDuping"}],"badges":[0]},{"user":"Mhmd_FVC","color":"#556977","offset":6844,"fragments":[{"text":"omega, beat my PB first"}],"badges":[0]},{"user":"Mhmd_FVC","color":"#556977","offset":6849,"fragments":[{"text":"we'll see who is truly betr"}],"badges":[0]},{"user":"Wiwaldo","color":"#D2691E","offset":6854,"fragments":[{"text":"PJSalt","emote":30}],"badges":[]},{"user":"jolzi","color":"#388585","offset":6854,"fragments":[{"text":"mh who is this omega even"}],"badges":[0]},{"user":"anti_","color":"#556977","offset":6857,"fragments":[{"text":"omega"}],"badges":[21]},{"user":"jolzi","color":"#388585","offset":6859,"fragments":[{"text":"does he have a vc am wr?"}],"badges":[0]},{"user":"anti_","color":"#556977","offset":6862,"fragments":[{"text":"someone"}],"badges":[21]},{"user":"anti_","color":"#556977","offset":6866,"fragments":[{"text":"whens not free wr"}],"badges":[21]},{"user":"scha_de","color":"#FF4500","offset":6868,"fragments":[{"text":"wr is 2:29:15 by mh - best possible time: 3:08:22 "},{"text":"MingLee","emote":22}],"badges":[]},{"user":"Mhmd_FVC","color":"#556977","offset":6906,"fragments":[{"text":"shit"}],"badges":[0]},{"user":"Mhmd_FVC","color":"#556977","offset":6909,"fragments":[{"text":"I've been exposed"}],"badges":[0]},{"user":"felyp244","color":"#DAA520","offset":6911,"fragments":[{"text":"Hi there , GL"}],"badges":[]},{"user":"Imahoodkingho","color":null,"offset":6922,"fragments":[{"text":"maybe he can beat his pb tho"}],"badges":[]},{"user":"mr_ptp","color":"#1E90FF","offset":6937,"fragments":[{"text":"nice flying son"}],"badges":[]},{"user":"anti_","color":"#556977","offset":6946,"fragments":[{"text":"woah mang"}],"badges":[21]},{"user":"anti_","color":"#556977","offset":6954,"fragments":[{"text":"you fly like a crazy bitch"}],"badges":[21]},{"user":"Mhmd_FVC","color":"#556977","offset":6956,"fragments":[{"text":"when's sub 4:20 demoman"}],"badges":[0]},{"user":"patrick_gta","color":"#D2691E","offset":6968,"fragments":[{"text":"how do you like rc raider pickup, btw?"}],"badges":[]},{"user":"Imahoodkingho","color":null,"offset":6969,"fragments":[{"text":"lol"}],"badges":[]},{"user":"patrick_gta","color":"#D2691E","offset":6983,"fragments":[{"text":"*find"}],"badges":[]},{"user":"Mhmd_FVC","color":"#556977","offset":6989,"fragments":[{"text":"fok"}],"badges":[0]},{"user":"Mhmd_FVC","color":"#556977","offset":6990,"fragments":[{"text":"eh"}],"badges":[0]},{"user":"Nozlar","color":"#8A2BE2","offset":7005,"fragments":[{"text":"Smilin"}],"badges":[8]},{"user":"Imahoodkingho","color":null,"offset":7015,"fragments":[{"text":"get that drilling"}],"badges":[]},{"user":"Imahoodkingho","color":null,"offset":7020,"fragments":[{"text":"lol"}],"badges":[]},{"user":"patrick_gta","color":"#D2691E","offset":7022,"fragments":[{"text":"anyone, omega"}],"badges":[]},{"user":"anti_","color":"#556977","offset":7029,"fragments":[{"text":"patrick"}],"badges":[21]},{"user":"anti_","color":"#556977","offset":7031,"fragments":[{"text":"its fast"}],"badges":[21]},{"user":"patrick_gta","color":"#D2691E","offset":7033,"fragments":[{"text":"including you^^"}],"badges":[]},{"user":"Imahoodkingho","color":null,"offset":7048,"fragments":[{"text":"what up patrick"}],"badges":[]},{"user":"mr_ptp","color":"#1E90FF","offset":7050,"fragments":[{"text":"Patrick_SDA triple dupe is great, now go find no escape instapass "},{"text":"OpieOP","emote":17}],"badges":[]},{"user":"Mhmd_FVC","color":"#556977","offset":7055,"fragments":[{"text":"is this supra 4:20"}],"badges":[0]},{"user":"Mhmd_FVC","color":"#556977","offset":7056,"fragments":[{"text":"then"}],"badges":[0]},{"user":"Mhmd_FVC","color":"#556977","offset":7062,"fragments":[{"text":"or no"}],"badges":[0]},{"user":"Mhmd_FVC","color":"#556977","offset":7063,"fragments":[{"text":"when*"}],"badges":[0]},{"user":"jolzi","color":"#388585","offset":7099,"fragments":[{"text":"0-1-2-3 order "},{"text":"DansGame","emote":3}],"badges":[0]},{"user":"jolzi","color":"#388585","offset":7104,"fragments":[{"text":"0-1-3-2 is faster"}],"badges":[0]},{"user":"anti_","color":"#556977","offset":7108,"fragments":[{"text":"Macface"}],"badges":[21]},{"user":"Heinki","color":"#FF0000","offset":7119,"fragments":[{"text":"BADDADANDEM"}],"badges":[0]},{"user":"mr_ptp","color":"#1E90FF","offset":7122,"fragments":[{"text":"jolzi"}],"badges":[]},{"user":"mr_ptp","color":"#1E90FF","offset":7129,"fragments":[{"text":"have you ever flipped monster truck in sa?"}],"badges":[]},{"user":"Heinki","color":"#FF0000","offset":7132,"fragments":[{"text":"!1v1 jolzi"}],"badges":[0]},{"user":"jolzi","color":"#388585","offset":7137,"fragments":[{"text":"pitp0 yes"}],"badges":[0]},{"user":"mr_ptp","color":"#1E90FF","offset":7140,"fragments":[{"text":"fok"}],"badges":[]},{"user":"Mhmd_FVC","color":"#556977","offset":7165,"fragments":[{"text":"also what's this triple dupe"}],"badges":[0]},{"user":"mr_ptp","color":"#1E90FF","offset":7181,"fragments":[{"text":"awos-stb-raider"}],"badges":[]},{"user":"Rapid_Influx","color":"#0000FF","offset":7181,"fragments":[{"text":"Jolzi has flipped the tank before now, the monster truck is nothing"}],"badges":[]},{"user":"jolzi","color":"#388585","offset":7183,"fragments":[{"text":"pitp0 https://www.twitch.tv/jolzi/v/43014971"}],"badges":[0]},{"user":"Mhmd_FVC","color":"#556977","offset":7197,"fragments":[{"text":"ah ye"}],"badges":[0]},{"user":"anti_","color":"#556977","offset":7209,"fragments":[{"text":"also em aych"}],"badges":[21]},{"user":"Mhmd_FVC","color":"#556977","offset":7225,"fragments":[{"text":"yes"}],"badges":[0]},{"user":"anti_","color":"#556977","offset":7249,"fragments":[{"text":"in your pb you rampage started vip via save marker, do you think it could be faster/safer with the 2nd taxi?"}],"badges":[21]},{"user":"anti_","color":"#556977","offset":7264,"fragments":[{"text":"like starting the rampage with taxi"}],"badges":[21]},{"user":"mr_ptp","color":"#1E90FF","offset":7267,"fragments":[{"text":"just mandupe "},{"text":"4Head","emote":2}],"badges":[]},{"user":"Mhmd_FVC","color":"#556977","offset":7273,"fragments":[{"text":"go away potpo"}],"badges":[0]},{"user":"anti_","color":"#556977","offset":7273,"fragments":[{"text":"no "},{"text":"4Head","emote":2}],"badges":[21]},{"user":"MestaYoku","color":"#FF0000","offset":7278,"fragments":[{"text":"Dang... I always miss love fist ruined my life/God bike..."}],"badges":[]},{"user":"mr_ptp","color":"#1E90FF","offset":7282,"fragments":[{"text":"manduping taxi missions is ez"}],"badges":[]},{"user":"Mhmd_FVC","color":"#556977","offset":7288,"fragments":[{"text":"idk why I didn't think of that antistreaks"}],"badges":[0]},{"user":"Mhmd_FVC","color":"#556977","offset":7292,"fragments":[{"text":"that + save replay"}],"badges":[0]},{"user":"mr_ptp","color":"#1E90FF","offset":7292,"fragments":[{"text":"10% consistency"}],"badges":[]},{"user":"anti_","color":"#556977","offset":7305,"fragments":[{"text":"yeah thats what i did right before i killed my run to being dumb"}],"badges":[21]},{"user":"Mhmd_FVC","color":"#556977","offset":7312,"fragments":[{"text":"payphone missions are literally the easiest mandupes btw"}],"badges":[0]},{"user":"Mhmd_FVC","color":"#556977","offset":7314,"fragments":[{"text":"TwoHands"}],"badges":[0]},{"user":"Mhmd_FVC","color":"#556977","offset":7330,"fragments":[{"text":"why even sWonder"}],"badges":[0]},{"user":"Mhmd_FVC","color":"#556977","offset":7342,"fragments":[{"text":"at least it didn't do anything but waste a few seconds"}],"badges":[0]},{"user":"Mhmd_FVC","color":"#556977","offset":7377,"fragments":[{"text":"snipe with tec9 isn't a great idea"}],"badges":[0]},{"user":"jolzi","color":"#388585","offset":7391,"fragments":[{"text":"dude"}],"badges":[0]},{"user":"anti_","color":"#556977","offset":7391,"fragments":[{"text":"tec9 fuhn"}],"badges":[21]},{"user":"jolzi","color":"#388585","offset":7393,"fragments":[{"text":"this is AM"}],"badges":[0]},{"user":"anti_","color":"#556977","offset":7401,"fragments":[{"text":"yes jolzi welcome"}],"badges":[21]},{"user":"jolzi","color":"#388585","offset":7402,"fragments":[{"text":"why doesn't the route get the police cheetah"}],"badges":[0]},{"user":"jolzi","color":"#388585","offset":7412,"fragments":[{"text":"it's free and on the way"}],"badges":[0]},{"user":"Mhmd_FVC","color":"#556977","offset":7419,"fragments":[{"text":"cause I just RNG another good car on the road"}],"badges":[0]},{"user":"Mhmd_FVC","color":"#556977","offset":7420,"fragments":[{"text":"OpieOP","emote":17}],"badges":[0]},{"user":"jolzi","color":"#388585","offset":7445,"fragments":[{"text":"fuck rng"}],"badges":[0]},{"user":"mr_ptp","color":"#1E90FF","offset":7467,"fragments":[{"text":"im terrible at routing "},{"text":">(","emote":6}],"badges":[]},{"user":"halu_","color":"#FF7F50","offset":7471,"fragments":[{"text":"hey Omega pick up the phone its Ray "},{"text":"Kappa","emote":7}],"badges":[]},{"user":"anti_","color":"#556977","offset":7484,"fragments":[{"text":"didnt get uzi sWonder"}],"badges":[21]},{"user":"WhyAmIMrPink","color":"#FF69B4","offset":7492,"fragments":[{"text":"Spare slice hype"}],"badges":[]},{"user":"anti_","color":"#556977","offset":7517,"fragments":[{"text":"whens more skype emotes"}],"badges":[21]},{"user":"Imahoodkingho","color":null,"offset":7635,"fragments":[{"text":"tealadFace"}],"badges":[]},{"user":"patrick_gta","color":"#D2691E","offset":7636,"fragments":[{"text":"lelreset: any proper results on timing if the stowaway skip is worth it?"}],"badges":[]},{"user":"jolzi","color":"#388585","offset":7662,"fragments":[{"text":"whens driveby shooting the taxis since you have a bike"}],"badges":[0]},{"user":"scha_de","color":"#FF4500","offset":7676,"fragments":[{"text":"whens going for that guy first"}],"badges":[]},{"user":"zekewho","color":"#FF69B4","offset":7693,"fragments":[{"text":"Vice City "},{"text":"PogChamp","emote":14}],"badges":[]},{"user":"jolzi","color":"#388585","offset":7696,"fragments":[{"text":"whens resetting the moment one car goes onto a bridge"}],"badges":[0]},{"user":"anti_","color":"#556977","offset":7712,"fragments":[{"text":"when wr is 1:25 at least"}],"badges":[21]},{"user":"Marlboro_Ford","color":"#FF4500","offset":7730,"fragments":[{"text":"when are we going to start sentences with the word \"when\" ?"}],"badges":[]},{"user":"Marlboro_Ford","color":"#FF4500","offset":7735,"fragments":[{"text":"Kappa","emote":7}],"badges":[]},{"user":"scha_de","color":"#FF4500","offset":7738,"fragments":[{"text":"not going for optimal pattern "},{"text":"DansGame","emote":3}],"badges":[]},{"user":"patrick_gta","color":"#D2691E","offset":7742,"fragments":[{"text":"you did some timing, co concluding that good timing is necessary"}],"badges":[]},{"user":"Imahoodkingho","color":null,"offset":7748,"fragments":[{"text":"DoILookLikeIKnowWhatAFrankerFaceZeeIs FcknBall"}],"badges":[]},{"user":"jolzi","color":"#388585","offset":7758,"fragments":[{"text":"2ndvan was good"}],"badges":[0]},{"user":"jolzi","color":"#388585","offset":7772,"fragments":[{"text":"don't land on the gunman jetty "},{"text":"TriHard","emote":31}],"badges":[0]},{"user":"Imahoodkingho","color":null,"offset":7785,"fragments":[{"text":"lol @ jolzi"}],"badges":[]},{"user":"Imahoodkingho","color":null,"offset":7802,"fragments":[{"text":"LookAtDis!!!"}],"badges":[]},{"user":"patrick_gta","color":"#D2691E","offset":7840,"fragments":[{"text":"what's the problem?"}],"badges":[]},{"user":"patrick_gta","color":"#D2691E","offset":7853,"fragments":[{"text":"or relevance"}],"badges":[]},{"user":"accuso1","color":"#0000FF","offset":7869,"fragments":[{"text":"gta:vc run? followed"}],"badges":[]},{"user":"patrick_gta","color":"#D2691E","offset":7880,"fragments":[{"text":"or do you mean while the game is running?"}],"badges":[]},{"user":"luke100ster","color":"#0000FF","offset":7882,"fragments":[{"text":"\"THEN IT HIT ME. CLOTHES ARE--\" \"not bad "},{"text":"OMGScoots","emote":32},{"text":" \""}],"badges":[]},{"user":"Graved","color":"#0000FF","offset":7889,"fragments":[{"text":"\"Hit me like a slippery fish\": https://www.youtube.com/watch?v=8ZyHdK_dGPc"}],"badges":[]},{"user":"luke100ster","color":"#0000FF","offset":7890,"fragments":[{"text":"that was perfect"}],"badges":[]},{"user":"WhyAmIMrPink","color":"#FF69B4","offset":7924,"fragments":[{"text":"No-one ever pickpcketed the naked guy. Where does he keep his wallet?"}],"badges":[]},{"user":"Imahoodkingho","color":null,"offset":7924,"fragments":[{"text":"lol get fish slapped bitch"}],"badges":[]},{"user":"Imahoodkingho","color":null,"offset":7926,"fragments":[{"text":"hahahaha"}],"badges":[]},{"user":"patrick_gta","color":"#D2691E","offset":8008,"fragments":[{"text":"there should be a hotkey solution"}],"badges":[]},{"user":"Wattage","color":"#8A2BE2","offset":8014,"fragments":[{"text":"He doesn't need a wallet if he swallows a card and pays contactless "},{"text":"KevinTurtle","emote":33}],"badges":[0,8]},{"user":"anti_","color":"#556977","offset":8044,"fragments":[{"text":"when i did sa duping on my shitty laptop i could dupe with affinity=4"}],"badges":[21]},{"user":"anti_","color":"#556977","offset":8155,"fragments":[{"text":"no"}],"badges":[21]},{"user":"anti_","color":"#556977","offset":8204,"fragments":[{"text":"hm"}],"badges":[21]},{"user":"patrick_gta","color":"#D2691E","offset":8234,"fragments":[{"text":"my mouse is reliable with my setup - only with win98 compatibility, though "},{"text":":D","emote":34}],"badges":[]},{"user":"Wattage","color":"#8A2BE2","offset":8251,"fragments":[{"text":"Never had an with steam version. But had many problems with retail"}],"badges":[0,8]},{"user":"anti_","color":"#556977","offset":8272,"fragments":[{"text":"it was reverse for me haworth"}],"badges":[21]},{"user":"anti_","color":"#556977","offset":8285,"fragments":[{"text":"steam version always had issues starting for me"}],"badges":[21]},{"user":"mr_ptp","color":"#1E90FF","offset":8293,"fragments":[{"text":"is it going to rain? :^"}],"badges":[]},{"user":"anti_","color":"#556977","offset":8322,"fragments":[{"text":"its 5:30 am"}],"badges":[21]},{"user":"anti_","color":"#556977","offset":8328,"fragments":[{"text":"im going into hibernation now"}],"badges":[21]},{"user":"anti_","color":"#556977","offset":8335,"fragments":[{"text":"goodbye"}],"badges":[21]},{"user":"Imahoodkingho","color":null,"offset":8342,"fragments":[{"text":"peace anti"}],"badges":[]},{"user":"Wattage","color":"#8A2BE2","offset":8347,"fragments":[{"text":"Bye"}],"badges":[0,8]},{"user":"Marlboro_Ford","color":"#FF4500","offset":8363,"fragments":[{"text":"miised chevkpoiny"}],"badges":[]},{"user":"Wattage","color":"#8A2BE2","offset":8371,"fragments":[{"text":"Ye"}],"badges":[0,8]},{"user":"Nimachakin","color":"#8A2BE2","offset":8383,"fragments":[{"text":"f*ck the rules "},{"text":"Kappa","emote":7}],"badges":[]},{"user":"mr_ptp","color":"#1E90FF","offset":8387,"fragments":[{"text":"seemsGood"}],"badges":[]},{"user":"Marlboro_Ford","color":"#FF4500","offset":8393,"fragments":[{"text":"bottom."}],"badges":[]},{"user":"Marlboro_Ford","color":"#FF4500","offset":8422,"fragments":[{"text":"southern most checkpoint"}],"badges":[]},{"user":"karl__k","color":"#008000","offset":8441,"fragments":[{"text":"dr1ver"}],"badges":[]},{"user":"karl__k","color":"#008000","offset":8443,"fragments":[{"text":"the mission"}],"badges":[]},{"user":"Heinki","color":"#FF0000","offset":8483,"fragments":[{"text":"alright im going to leave again need some sleep before the competition"}],"badges":[0]},{"user":"WhyAmIMrPink","color":"#FF69B4","offset":8497,"fragments":[{"text":"I might like you better if we slept together "},{"text":"Kreygasm","emote":1}],"badges":[]},{"user":"xk3axx","color":"#FF7F50","offset":8660,"fragments":[{"text":"Hey omega"}],"badges":[]},{"user":"karl__k","color":"#008000","offset":8667,"fragments":[{"text":"omega when is night vision, getting dark out there"}],"badges":[]},{"user":"CasterTM","color":null,"offset":8682,"fragments":[{"text":"hi omega, good luck"}],"badges":[]},{"user":"xk3axx","color":"#FF7F50","offset":8685,"fragments":[{"text":"Hey Karl"}],"badges":[]},{"user":"karl__k","color":"#008000","offset":8699,"fragments":[{"text":"hi"}],"badges":[]},{"user":"CasterTM","color":null,"offset":8708,"fragments":[{"text":"karl, for gta am, i've found another set-up which should work"}],"badges":[]},{"user":"CasterTM","color":null,"offset":8723,"fragments":[{"text":"with few rerouting"}],"badges":[]},{"user":"karl__k","color":"#008000","offset":8742,"fragments":[{"text":"k, whisper me I guess, so we dont shit up omegas chat"}],"badges":[]},{"user":"CasterTM","color":null,"offset":8750,"fragments":[{"text":"ok"}],"badges":[]},{"user":"Graved","color":"#0000FF","offset":8779,"fragments":[{"text":"Every PayDay 2 heist ever "},{"text":"Kappa","emote":7}],"badges":[]},{"user":"wewobulost","color":"#FF0000","offset":8935,"fragments":[{"text":"ThunBeast","emote":35}],"badges":[]},{"user":"tanalbi","color":"#0000FF","offset":9035,"fragments":[{"text":"In real life there's no way a bank heis like that is as simple as this one xD"}],"badges":[]},{"user":"cheeze____","color":"#DAA520","offset":9470,"fragments":[{"text":"miltDuck","emote":36},{"text":" Go Ω Go "},{"text":"miltDuck","emote":36}],"badges":[]},{"user":"caine1232","color":"#0000FF","offset":9500,"fragments":[{"text":"yeeDefinitely better than mhmd "},{"text":"Kappa","emote":7}],"badges":[]},{"user":"mr_ptp","color":"#1E90FF","offset":9600,"fragments":[{"text":"hang on"}],"badges":[]},{"user":"mr_ptp","color":"#1E90FF","offset":9610,"fragments":[{"text":"you can start juju scramble after cabmaggedon instapass?"}],"badges":[]},{"user":"cheeze____","color":"#DAA520","offset":9626,"fragments":[{"text":"Oh no I think this run isn't gonna be wr "},{"text":"BibleThump","emote":18}],"badges":[]},{"user":"mr_ptp","color":"#1E90FF","offset":9646,"fragments":[{"text":"ok im retarded "},{"text":"FailFish","emote":37}],"badges":[]},{"user":"AnnenizSmurf","color":"#FF0000","offset":9703,"fragments":[{"text":"vice city wtf?"}],"badges":[]},{"user":"felyp244","color":"#DAA520","offset":9725,"fragments":[{"text":"no warp for you"}],"badges":[]},{"user":"cheeze____","color":"#DAA520","offset":9726,"fragments":[{"text":"There's drunk people outside my house screaming stuff "},{"text":"DansGame","emote":3}],"badges":[]},{"user":"cazpersky","color":"#FF0000","offset":9742,"fragments":[{"text":"Join them "},{"text":"Kappa","emote":7}],"badges":[]},{"user":"sundew58","color":"#1E90FF","offset":9744,"fragments":[{"text":"yo omega gl"}],"badges":[]},{"user":"cheeze____","color":"#DAA520","offset":9757,"fragments":[{"text":"Kappa","emote":7}],"badges":[]},{"user":"cheeze____","color":"#DAA520","offset":9821,"fragments":[{"text":"I ate all cheeseburgers but I could give them some icecream "},{"text":"Kappa","emote":7}],"badges":[]},{"user":"Mhmd_FVC","color":"#556977","offset":9826,"fragments":[{"text":"drunk people screaming?"}],"badges":[0]},{"user":"Mhmd_FVC","color":"#556977","offset":9831,"fragments":[{"text":"\"MY KAAZIN IS HERE!\""}],"badges":[0]},{"user":"cazpersky","color":"#FF0000","offset":9845,"fragments":[{"text":"lol"}],"badges":[]},{"user":"cheeze____","color":"#DAA520","offset":9853,"fragments":[{"text":"miltWa","emote":4}],"badges":[]},{"user":"cheeze____","color":"#DAA520","offset":9875,"fragments":[{"text":"Yup."}],"badges":[]},{"user":"cazpersky","color":"#FF0000","offset":9908,"fragments":[{"text":"Nice Cheetah son"}],"badges":[]},{"user":"Mhmd_FVC","color":"#556977","offset":9908,"fragments":[{"text":"where I live in general has people who aren't really dicks"}],"badges":[0]},{"user":"Mhmd_FVC","color":"#556977","offset":9910,"fragments":[{"text":"p. good"}],"badges":[0]},{"user":"Mhmd_FVC","color":"#556977","offset":9982,"fragments":[{"text":"a lot of the time if they do take that bridge they drown themselves anyway"}],"badges":[0]},{"user":"Mhmd_FVC","color":"#556977","offset":9982,"fragments":[{"text":"at least"}],"badges":[0]},{"user":"Mhmd_FVC","color":"#556977","offset":10011,"fragments":[{"text":"ew"}],"badges":[0]},{"user":"Mhmd_FVC","color":"#556977","offset":10033,"fragments":[{"text":"man"}],"badges":[0]},{"user":"Mhmd_FVC","color":"#556977","offset":10037,"fragments":[{"text":"if only taxi 3 instapass wasn't a thing"}],"badges":[0]},{"user":"Eetu772","color":"#2E8B57","offset":10041,"fragments":[{"text":"hi omega, good luck "},{"text":"OpieOP","emote":17},{"text":" /"}],"badges":[]},{"user":"Mhmd_FVC","color":"#556977","offset":10043,"fragments":[{"text":"could just do boatyard and ctc is less annoying"}],"badges":[0]},{"user":"jolzi","color":"#388585","offset":10045,"fragments":[{"text":"i had 5 glitched cars"}],"badges":[0]},{"user":"cheeze____","color":"#DAA520","offset":10056,"fragments":[{"text":"lmao"}],"badges":[]},{"user":"jolzi","color":"#388585","offset":10059,"fragments":[{"text":"1 went to malibu over starfish"}],"badges":[0]},{"user":"Mhmd_FVC","color":"#556977","offset":10060,"fragments":[{"text":"OpieOP","emote":17}],"badges":[0]},{"user":"Eetu772","color":"#2E8B57","offset":10064,"fragments":[{"text":"wow "},{"text":"Kappa","emote":7}],"badges":[]},{"user":"felyp244","color":"#DAA520","offset":10068,"fragments":[{"text":"yesUltracop"}],"badges":[]},{"user":"jolzi","color":"#388585","offset":10071,"fragments":[{"text":"and 2 was stuck at cherry poppers"}],"badges":[0]},{"user":"cheeze____","color":"#DAA520","offset":10072,"fragments":[{"text":"Oh my god"}],"badges":[]},{"user":"killerkieke","color":"#8A2BE2","offset":10079,"fragments":[{"text":"nice mission"}],"badges":[]},{"user":"mr_ptp","color":"#1E90FF","offset":10087,"fragments":[{"text":"good bike"}],"badges":[]},{"user":"Sorak11","color":"#0000FF","offset":10090,"fragments":[{"text":"haha wtf"}],"badges":[]},{"user":"felyp244","color":"#DAA520","offset":10093,"fragments":[{"text":"wtf"}],"badges":[]},{"user":"Nimachakin","color":"#8A2BE2","offset":10094,"fragments":[{"text":"loooool"}],"badges":[]},{"user":"Mhmd_FVC","color":"#556977","offset":10094,"fragments":[{"text":"4Head","emote":2}],"badges":[0]},{"user":"tullam0re_dew","color":null,"offset":10094,"fragments":[{"text":"WTF "},{"text":":D","emote":34}],"badges":[]},{"user":"cheeze____","color":"#DAA520","offset":10096,"fragments":[{"text":"hahaahahaha"}],"badges":[]},{"user":"felyp244","color":"#DAA520","offset":10098,"fragments":[{"text":"LMAO"}],"badges":[]},{"user":"CasterTM","color":null,"offset":10103,"fragments":[{"text":"lol"}],"badges":[]},{"user":"tullam0re_dew","color":null,"offset":10104,"fragments":[{"text":"Kappa","emote":7}],"badges":[]},{"user":"soarsexx","color":"#1E90FF","offset":10104,"fragments":[{"text":"Ghost rider"}],"badges":[]},{"user":"cheeze____","color":"#DAA520","offset":10105,"fragments":[{"text":"what the fuck"}],"badges":[]},{"user":"caine1232","color":"#0000FF","offset":10108,"fragments":[{"text":"Ghost collectors "},{"text":"EleGiggle","emote":19}],"badges":[]},{"user":"CasterTM","color":null,"offset":10108,"fragments":[{"text":"i like that"}],"badges":[]},{"user":"Eetu772","color":"#2E8B57","offset":10111,"fragments":[{"text":"i can already tell this is gonna be fun "},{"text":"Kappa","emote":7}],"badges":[]},{"user":"felyp244","color":"#DAA520","offset":10242,"fragments":[{"text":"watchout the faggio dudes are comming"}],"badges":[]},{"user":"jolzi","color":"#388585","offset":10341,"fragments":[{"text":"rip faggio crew"}],"badges":[0]},{"user":"felyp244","color":"#DAA520","offset":10364,"fragments":[{"text":"rip replay"}],"badges":[]},{"user":"jolzi","color":"#388585","offset":10375,"fragments":[{"text":"riplay"}],"badges":[0]},{"user":"killerkieke","color":"#8A2BE2","offset":10440,"fragments":[{"text":"how does this phonecall thing work?"}],"badges":[]},{"user":"Mhmd_FVC","color":"#556977","offset":10467,"fragments":[{"text":"it's related to the fact that action (on foot) and radio (in car) is the same button on PS2"}],"badges":[0]},{"user":"Mhmd_FVC","color":"#556977","offset":10475,"fragments":[{"text":"so if you have one key bound to both on PC"}],"badges":[0]},{"user":"Mhmd_FVC","color":"#556977","offset":10487,"fragments":[{"text":"it can hold calls through getting into vehicles"}],"badges":[0]},{"user":"Mhmd_FVC","color":"#556977","offset":10497,"fragments":[{"text":"cause it's the \"same button\" you're holding"}],"badges":[0]},{"user":"Mhmd_FVC","color":"#556977","offset":10499,"fragments":[{"text":"I guess"}],"badges":[0]},{"user":"Mhmd_FVC","color":"#556977","offset":10508,"fragments":[{"text":"a little after SA call holding lelreset"}],"badges":[0]},{"user":"Mhmd_FVC","color":"#556977","offset":10509,"fragments":[{"text":"I think"}],"badges":[0]},{"user":"jolzi","color":"#388585","offset":10528,"fragments":[{"text":"you have cap the collectors already"}],"badges":[0]},{"user":"jolzi","color":"#388585","offset":10537,"fragments":[{"text":"you did it 2 missions ago "},{"text":"DansGame","emote":3}],"badges":[0]},{"user":"Mhmd_FVC","color":"#556977","offset":10548,"fragments":[{"text":"wait a sec"}],"badges":[0]},{"user":"Mhmd_FVC","color":"#556977","offset":10550,"fragments":[{"text":"did you cancel the call?"}],"badges":[0]},{"user":"Nimachakin","color":"#8A2BE2","offset":10569,"fragments":[{"text":"big cojones "},{"text":"Kreygasm","emote":1}],"badges":[]},{"user":"skudstream","color":"#32244C","offset":10571,"fragments":[{"text":"any reason for the foreign version? faster?"}],"badges":[]},{"user":"Mhmd_FVC","color":"#556977","offset":10586,"fragments":[{"text":"if you did then take the calls in queue before you do trojan"}],"badges":[0]},{"user":"Mhmd_FVC","color":"#556977","offset":10586,"fragments":[{"text":"ofc"}],"badges":[0]},{"user":"felyp244","color":"#DAA520","offset":10612,"fragments":[{"text":"that sniper ***"}],"badges":[]},{"user":"Mhmd_FVC","color":"#556977","offset":10613,"fragments":[{"text":"and yeah TheSkudDestroyer"}],"badges":[0]},{"user":"skudstream","color":"#32244C","offset":10618,"fragments":[{"text":"I just haven't seen other runners doing foreign VC or SA, but it's no surprise."}],"badges":[]},{"user":"Mhmd_FVC","color":"#556977","offset":10624,"fragments":[{"text":"http://pastebin.com/rA157UJW"}],"badges":[0]},{"user":"skudstream","color":"#32244C","offset":10627,"fragments":[{"text":"I also have not watched a lot of runs for a few months"}],"badges":[]},{"user":"skudstream","color":"#32244C","offset":10707,"fragments":[{"text":"I see. Cherry Poppers is a bitch anyway"}],"badges":[]}],"images":[{"classes":[],"path":"moderator-1","title":"Moderator"},{"classes":["ttv-emote"],"path":"ttv/41"},{"classes":["ttv-emote"],"path":"ttv/354"},{"classes":["ttv-emote"],"path":"ttv/33"},{"classes":["ttv-emote"],"path":"ttv/26708"},{"classes":["ttv-emote"],"path":"ttv/25322"},{"classes":["ttv-emote"],"path":"ttv/4"},{"classes":["ttv-emote"],"path":"ttv/25"},{"classes":["sub-badge"],"path":"ultimaomega07-subscriber-1","title":"Subscriber"},{"classes":["ttv-emote"],"path":"ttv/91144"},{"classes":["ttv-emote"],"path":"ttv/98562"},{"classes":["ttv-emote"],"path":"ttv/66"},{"classes":["ttv-emote"],"path":"ttv/28087"},{"classes":["ttv-emote"],"path":"ttv/76171"},{"classes":["ttv-emote"],"path":"ttv/88"},{"classes":["ttv-emote"],"path":"ttv/66935"},{"classes":["ttv-emote"],"path":"ttv/89009"},{"classes":["ttv-emote"],"path":"ttv/356"},{"classes":["ttv-emote"],"path":"ttv/86"},{"classes":["ttv-emote"],"path":"ttv/4339"},{"classes":["ttv-emote"],"path":"ttv/84608"},{"classes":["prime-badge"],"path":"turbo-1","title":"Turbo"},{"classes":["ttv-emote"],"path":"ttv/68856"},{"classes":["ttv-emote"],"path":"ttv/54403"},{"classes":["ttv-emote"],"path":"ttv/2"},{"classes":["ttv-emote"],"path":"ttv/64138"},{"classes":["ttv-emote"],"path":"ttv/1902"},{"classes":["ttv-emote"],"path":"ttv/9"},{"classes":["ttv-emote"],"path":"ttv/65"},{"classes":["ttv-emote"],"path":"ttv/1906"},{"classes":["ttv-emote"],"path":"ttv/36"},{"classes":["ttv-emote"],"path":"ttv/171"},{"classes":["ttv-emote"],"path":"ttv/91"},{"classes":["ttv-emote"],"path":"ttv/40"},{"classes":["ttv-emote"],"path":"ttv/3"},{"classes":["ttv-emote"],"path":"ttv/1898"},{"classes":["ttv-emote"],"path":"ttv/25154"},{"classes":["ttv-emote"],"path":"ttv/360"}]}